{
  "ok": true,
  "engine": "v8_9_1_alert_decision_center_calibrated",
  "generatedAt": "2026-07-05T08:14:18.351Z",
  "total": 56,
  "summary": {
    "critical": 20,
    "warning": 12,
    "opportunity": 8,
    "watch": 14,
    "info": 2,
    "urgent": 20,
    "important": 12
  },
  "suppressed": {
    "critical": 15,
    "warning": 131,
    "opportunity": 6,
    "watch": 0,
    "info": 0
  },
  "alerts": [
    {
      "id": "price:price_conflict:ACAMD:تعارض سعر",
      "level": "critical",
      "priority": "عاجل",
      "source": "price",
      "type": "price_conflict",
      "symbol": "ACAMD",
      "title": "تعارض سعر",
      "text": "final=2.27, recommendation=2.25, market=2.27, cache=2.25",
      "action": "مراجعة السعر قبل أي قرار قوي",
      "why": "max/min internal price spread 0.89%"
    },
    {
      "id": "price:price_conflict:ACAP:تعارض سعر",
      "level": "critical",
      "priority": "عاجل",
      "source": "price",
      "type": "price_conflict",
      "symbol": "ACAP",
      "title": "تعارض سعر",
      "text": "final=8.67, recommendation=8.56, market=8.67, cache=8.56",
      "action": "مراجعة السعر قبل أي قرار قوي",
      "why": "max/min internal price spread 1.29%"
    },
    {
      "id": "price:price_conflict:ACGC:تعارض سعر",
      "level": "critical",
      "priority": "عاجل",
      "source": "price",
      "type": "price_conflict",
      "symbol": "ACGC",
      "title": "تعارض سعر",
      "text": "final=9.3, recommendation=9.23, market=9.3, cache=9.23",
      "action": "مراجعة السعر قبل أي قرار قوي",
      "why": "max/min internal price spread 0.76%"
    },
    {
      "id": "price:price_conflict:ADIB:تعارض سعر",
      "level": "critical",
      "priority": "عاجل",
      "source": "price",
      "type": "price_conflict",
      "symbol": "ADIB",
      "title": "تعارض سعر",
      "text": "final=47.03, recommendation=46.64, market=47.03, cache=46.64",
      "action": "مراجعة السعر قبل أي قرار قوي",
      "why": "max/min internal price spread 0.84%"
    },
    {
      "id": "price:price_conflict:AFMC:تعارض سعر",
      "level": "critical",
      "priority": "عاجل",
      "source": "price",
      "type": "price_conflict",
      "symbol": "AFMC",
      "title": "تعارض سعر",
      "text": "final=68.21, recommendation=69.44, market=68.21, cache=69.44",
      "action": "مراجعة السعر قبل أي قرار قوي",
      "why": "max/min internal price spread 1.80%"
    },
    {
      "id": "price:price_conflict:AIFI:تعارض سعر",
      "level": "critical",
      "priority": "عاجل",
      "source": "price",
      "type": "price_conflict",
      "symbol": "AIFI",
      "title": "تعارض سعر",
      "text": "final=2, recommendation=null, market=2, cache=null",
      "action": "مراجعة السعر قبل أي قرار قوي",
      "why": "max/min internal price spread 1.00%"
    },
    {
      "id": "price:price_conflict:ALUM:تعارض سعر",
      "level": "critical",
      "priority": "عاجل",
      "source": "price",
      "type": "price_conflict",
      "symbol": "ALUM",
      "title": "تعارض سعر",
      "text": "final=21.71, recommendation=21.45, market=21.71, cache=21.45",
      "action": "مراجعة السعر قبل أي قرار قوي",
      "why": "max/min internal price spread 1.21%"
    },
    {
      "id": "price:price_conflict:AMER:تعارض سعر",
      "level": "critical",
      "priority": "عاجل",
      "source": "price",
      "type": "price_conflict",
      "symbol": "AMER",
      "title": "تعارض سعر",
      "text": "final=2.46, recommendation=2.42, market=2.46, cache=2.42",
      "action": "مراجعة السعر قبل أي قرار قوي",
      "why": "max/min internal price spread 1.65%"
    },
    {
      "id": "price:price_conflict:AMES:تعارض سعر",
      "level": "critical",
      "priority": "عاجل",
      "source": "price",
      "type": "price_conflict",
      "symbol": "AMES",
      "title": "تعارض سعر",
      "text": "final=59.95, recommendation=60.51, market=59.95, cache=60.51",
      "action": "مراجعة السعر قبل أي قرار قوي",
      "why": "max/min internal price spread 0.93%"
    },
    {
      "id": "price:price_conflict:AMOC:تعارض سعر",
      "level": "critical",
      "priority": "عاجل",
      "source": "price",
      "type": "price_conflict",
      "symbol": "AMOC",
      "title": "تعارض سعر",
      "text": "final=7.84, recommendation=7.76, market=7.84, cache=7.76",
      "action": "مراجعة السعر قبل أي قرار قوي",
      "why": "max/min internal price spread 1.03%"
    },
    {
      "id": "price:price_conflict:APSW:تعارض سعر",
      "level": "critical",
      "priority": "عاجل",
      "source": "price",
      "type": "price_conflict",
      "symbol": "APSW",
      "title": "تعارض سعر",
      "text": "final=8.35, recommendation=8.48, market=8.35, cache=8.48",
      "action": "مراجعة السعر قبل أي قرار قوي",
      "why": "max/min internal price spread 1.56%"
    },
    {
      "id": "price:price_conflict:ARCC:تعارض سعر",
      "level": "critical",
      "priority": "عاجل",
      "source": "price",
      "type": "price_conflict",
      "symbol": "ARCC",
      "title": "تعارض سعر",
      "text": "final=56.35, recommendation=55.44, market=56.35, cache=55.44",
      "action": "مراجعة السعر قبل أي قرار قوي",
      "why": "max/min internal price spread 1.64%"
    },
    {
      "id": "price:price_conflict:AREH:تعارض سعر",
      "level": "critical",
      "priority": "عاجل",
      "source": "price",
      "type": "price_conflict",
      "symbol": "AREH",
      "title": "تعارض سعر",
      "text": "final=1.59, recommendation=1.56, market=1.59, cache=1.56",
      "action": "مراجعة السعر قبل أي قرار قوي",
      "why": "max/min internal price spread 1.92%"
    },
    {
      "id": "price:price_conflict:ASCM:تعارض سعر",
      "level": "critical",
      "priority": "عاجل",
      "source": "price",
      "type": "price_conflict",
      "symbol": "ASCM",
      "title": "تعارض سعر",
      "text": "final=60.92, recommendation=59.26, market=60.92, cache=59.26",
      "action": "مراجعة السعر قبل أي قرار قوي",
      "why": "max/min internal price spread 2.80%"
    },
    {
      "id": "price:price_conflict:ATQA:تعارض سعر",
      "level": "critical",
      "priority": "عاجل",
      "source": "price",
      "type": "price_conflict",
      "symbol": "ATQA",
      "title": "تعارض سعر",
      "text": "final=9.55, recommendation=9.47, market=9.55, cache=9.47",
      "action": "مراجعة السعر قبل أي قرار قوي",
      "why": "max/min internal price spread 0.84%"
    },
    {
      "id": "price:price_conflict:AXPH:تعارض سعر",
      "level": "critical",
      "priority": "عاجل",
      "source": "price",
      "type": "price_conflict",
      "symbol": "AXPH",
      "title": "تعارض سعر",
      "text": "final=1241.09, recommendation=1212.35, market=1241.09, cache=1212.35",
      "action": "مراجعة السعر قبل أي قرار قوي",
      "why": "max/min internal price spread 2.37%"
    },
    {
      "id": "price:price_conflict:BINV:تعارض سعر",
      "level": "critical",
      "priority": "عاجل",
      "source": "price",
      "type": "price_conflict",
      "symbol": "BINV",
      "title": "تعارض سعر",
      "text": "final=47.82, recommendation=46.04, market=47.82, cache=46.04",
      "action": "مراجعة السعر قبل أي قرار قوي",
      "why": "max/min internal price spread 3.87%"
    },
    {
      "id": "price:price_conflict:BIOC:تعارض سعر",
      "level": "critical",
      "priority": "عاجل",
      "source": "price",
      "type": "price_conflict",
      "symbol": "BIOC",
      "title": "تعارض سعر",
      "text": "final=72.62, recommendation=71.48, market=72.62, cache=71.48",
      "action": "مراجعة السعر قبل أي قرار قوي",
      "why": "max/min internal price spread 1.59%"
    },
    {
      "id": "price:price_conflict:BONY:تعارض سعر",
      "level": "critical",
      "priority": "عاجل",
      "source": "price",
      "type": "price_conflict",
      "symbol": "BONY",
      "title": "تعارض سعر",
      "text": "final=4.94, recommendation=4.88, market=4.94, cache=4.88",
      "action": "مراجعة السعر قبل أي قرار قوي",
      "why": "max/min internal price spread 1.23%"
    },
    {
      "id": "price:price_conflict:BTFH:تعارض سعر",
      "level": "critical",
      "priority": "عاجل",
      "source": "price",
      "type": "price_conflict",
      "symbol": "BTFH",
      "title": "تعارض سعر",
      "text": "final=3.01, recommendation=2.97, market=3.01, cache=2.97",
      "action": "مراجعة السعر قبل أي قرار قوي",
      "why": "max/min internal price spread 1.35%"
    },
    {
      "id": "price:stale_price_summary:market:28 أسعار قديمة/غير مؤكدة",
      "level": "warning",
      "priority": "مهم",
      "source": "price",
      "type": "stale_price_summary",
      "symbol": null,
      "title": "28 أسعار قديمة/غير مؤكدة",
      "text": "أمثلة: ARVA, CEFM, EDFM, EFIC, EGAS, EGBE, ELNA, ELWA, EOSB, EPPK, FERC, GRCA, GTEX, ICID",
      "action": "شغّل Workflow مرة واحدة فقط أو انتظر تحديث المصدر",
      "why": "تم دمج الأسعار القديمة في تنبيه واحد بدل عشرات التنبيهات"
    },
    {
      "id": "price:stale_price_summary:market:38 أسعار تحتاج تحديث/تحقق",
      "level": "warning",
      "priority": "مهم",
      "source": "price",
      "type": "stale_price_summary",
      "symbol": null,
      "title": "38 أسعار تحتاج تحديث/تحقق",
      "text": "أمثلة: AFMC, AIFI, AJWA, AMIA, APSW, ARVA, BINV, CEFM, DAPH, EAST, EDFM, EFIC",
      "action": "شغّل Workflow مرة واحدة فقط أو انتظر تحديث المصدر؛ لا تكرر التشغيل بلا داعٍ",
      "why": "تم تجميع الأسعار القديمة في تنبيه واحد لتقليل الضوضاء"
    },
    {
      "id": "ranking:blocked_candidate:VLMR:مرشح مقيّد لا يرفع للأولوية",
      "level": "warning",
      "priority": "مهم",
      "source": "ranking",
      "type": "blocked_candidate",
      "symbol": "VLMR",
      "title": "مرشح مقيّد لا يرفع للأولوية",
      "text": "تعارض سعر",
      "action": "اتركه للمراقبة فقط حتى تزول القيود",
      "why": "القيود تخفض صلاحية السهم كفرصة تنفيذية"
    },
    {
      "id": "ranking:blocked_candidate:CIRA:مرشح مقيّد لا يرفع للأولوية",
      "level": "warning",
      "priority": "مهم",
      "source": "ranking",
      "type": "blocked_candidate",
      "symbol": "CIRA",
      "title": "مرشح مقيّد لا يرفع للأولوية",
      "text": "تعارض سعر",
      "action": "اتركه للمراقبة فقط حتى تزول القيود",
      "why": "القيود تخفض صلاحية السهم كفرصة تنفيذية"
    },
    {
      "id": "ranking:blocked_candidate:FAIT:مرشح مقيّد لا يرفع للأولوية",
      "level": "warning",
      "priority": "مهم",
      "source": "ranking",
      "type": "blocked_candidate",
      "symbol": "FAIT",
      "title": "مرشح مقيّد لا يرفع للأولوية",
      "text": "تعارض سعر",
      "action": "اتركه للمراقبة فقط حتى تزول القيود",
      "why": "القيود تخفض صلاحية السهم كفرصة تنفيذية"
    },
    {
      "id": "ranking:blocked_candidate:GTWL:مرشح مقيّد لا يرفع للأولوية",
      "level": "warning",
      "priority": "مهم",
      "source": "ranking",
      "type": "blocked_candidate",
      "symbol": "GTWL",
      "title": "مرشح مقيّد لا يرفع للأولوية",
      "text": "تعارض سعر، R/R ضعيف",
      "action": "اتركه للمراقبة فقط حتى تزول القيود",
      "why": "القيود تخفض صلاحية السهم كفرصة تنفيذية"
    },
    {
      "id": "ranking:blocked_candidate:OLFI:مرشح مقيّد لا يرفع للأولوية",
      "level": "warning",
      "priority": "مهم",
      "source": "ranking",
      "type": "blocked_candidate",
      "symbol": "OLFI",
      "title": "مرشح مقيّد لا يرفع للأولوية",
      "text": "تعارض سعر",
      "action": "اتركه للمراقبة فقط حتى تزول القيود",
      "why": "القيود تخفض صلاحية السهم كفرصة تنفيذية"
    },
    {
      "id": "ranking:blocked_candidate:MPRC:مرشح مقيّد لا يرفع للأولوية",
      "level": "warning",
      "priority": "مهم",
      "source": "ranking",
      "type": "blocked_candidate",
      "symbol": "MPRC",
      "title": "مرشح مقيّد لا يرفع للأولوية",
      "text": "تعارض سعر",
      "action": "اتركه للمراقبة فقط حتى تزول القيود",
      "why": "القيود تخفض صلاحية السهم كفرصة تنفيذية"
    },
    {
      "id": "ranking:blocked_candidate:ELSH:مرشح مقيّد لا يرفع للأولوية",
      "level": "warning",
      "priority": "مهم",
      "source": "ranking",
      "type": "blocked_candidate",
      "symbol": "ELSH",
      "title": "مرشح مقيّد لا يرفع للأولوية",
      "text": "تعارض سعر، R/R ضعيف",
      "action": "اتركه للمراقبة فقط حتى تزول القيود",
      "why": "القيود تخفض صلاحية السهم كفرصة تنفيذية"
    },
    {
      "id": "ranking:blocked_candidate:MICH:مرشح مقيّد لا يرفع للأولوية",
      "level": "warning",
      "priority": "مهم",
      "source": "ranking",
      "type": "blocked_candidate",
      "symbol": "MICH",
      "title": "مرشح مقيّد لا يرفع للأولوية",
      "text": "تعارض سعر، R/R ضعيف",
      "action": "اتركه للمراقبة فقط حتى تزول القيود",
      "why": "القيود تخفض صلاحية السهم كفرصة تنفيذية"
    },
    {
      "id": "ranking:blocked_candidate:EBSC:مرشح مقيّد لا يرفع للأولوية",
      "level": "warning",
      "priority": "مهم",
      "source": "ranking",
      "type": "blocked_candidate",
      "symbol": "EBSC",
      "title": "مرشح مقيّد لا يرفع للأولوية",
      "text": "تعارض سعر، R/R ضعيف",
      "action": "اتركه للمراقبة فقط حتى تزول القيود",
      "why": "القيود تخفض صلاحية السهم كفرصة تنفيذية"
    },
    {
      "id": "ranking:blocked_candidate:KABO:مرشح مقيّد لا يرفع للأولوية",
      "level": "warning",
      "priority": "مهم",
      "source": "ranking",
      "type": "blocked_candidate",
      "symbol": "KABO",
      "title": "مرشح مقيّد لا يرفع للأولوية",
      "text": "تعارض سعر، R/R ضعيف",
      "action": "اتركه للمراقبة فقط حتى تزول القيود",
      "why": "القيود تخفض صلاحية السهم كفرصة تنفيذية"
    },
    {
      "id": "ranking:p1_opportunity:ROTO:P1 فرصة قوية #1",
      "level": "opportunity",
      "priority": "مراقبة قوية",
      "source": "ranking",
      "type": "p1_opportunity",
      "symbol": "ROTO",
      "title": "P1 فرصة قوية #1",
      "text": "prob=78% expected=5.35% rr=1.12",
      "action": "راجع الدخول والوقف وحجم الصفقة",
      "why": "احتمال الهدف 78% | ربح هدف1 9.2% | عائد متوقع 5.4% | R/R 1.12 | السعر مدقق | تاريخ 4/50"
    },
    {
      "id": "ranking:p1_opportunity:COPR:P1 فرصة قوية #2",
      "level": "opportunity",
      "priority": "مراقبة قوية",
      "source": "ranking",
      "type": "p1_opportunity",
      "symbol": "COPR",
      "title": "P1 فرصة قوية #2",
      "text": "prob=78% expected=3.11% rr=1",
      "action": "راجع الدخول والوقف وحجم الصفقة",
      "why": "احتمال الهدف 78% | ربح هدف1 5.6% | عائد متوقع 3.1% | R/R 1.00 | السعر مدقق | تاريخ 4/50"
    },
    {
      "id": "ranking:p1_opportunity:ARAB:P1 فرصة قوية #3",
      "level": "opportunity",
      "priority": "مراقبة قوية",
      "source": "ranking",
      "type": "p1_opportunity",
      "symbol": "ARAB",
      "title": "P1 فرصة قوية #3",
      "text": "prob=78% expected=2.67% rr=1",
      "action": "راجع الدخول والوقف وحجم الصفقة",
      "why": "احتمال الهدف 78% | ربح هدف1 4.8% | عائد متوقع 2.7% | R/R 1.00 | السعر مدقق | تاريخ 4/50"
    },
    {
      "id": "ranking:p1_opportunity:DOMT:P1 فرصة قوية #4",
      "level": "opportunity",
      "priority": "مراقبة قوية",
      "source": "ranking",
      "type": "p1_opportunity",
      "symbol": "DOMT",
      "title": "P1 فرصة قوية #4",
      "text": "prob=78% expected=2.62% rr=1.01",
      "action": "راجع الدخول والوقف وحجم الصفقة",
      "why": "احتمال الهدف 78% | ربح هدف1 4.7% | عائد متوقع 2.6% | R/R 1.01 | السعر مدقق | تاريخ 5/50"
    },
    {
      "id": "ranking:p1_opportunity:SPMD:P1 فرصة قوية #5",
      "level": "opportunity",
      "priority": "مراقبة قوية",
      "source": "ranking",
      "type": "p1_opportunity",
      "symbol": "SPMD",
      "title": "P1 فرصة قوية #5",
      "text": "prob=78% expected=2.6% rr=1",
      "action": "راجع الدخول والوقف وحجم الصفقة",
      "why": "احتمال الهدف 78% | ربح هدف1 4.7% | عائد متوقع 2.6% | R/R 1.00 | السعر مدقق | تاريخ 4/50"
    },
    {
      "id": "ranking:ranked_opportunity:ETRS:P1 — فرصة مرتبة #1",
      "level": "opportunity",
      "priority": "مراقبة قوية",
      "source": "ranking",
      "type": "ranked_opportunity",
      "symbol": "ETRS",
      "title": "P1 — فرصة مرتبة #1",
      "text": "الثقة 79% | R/R 1.33 | عائد متوقع 4.6%",
      "action": "راجع سعر الدخول والوقف قبل أي قرار، والبيانات عامة ومتأخرة",
      "why": "احتمال الهدف 79% | ربح هدف1 7.2% | عائد متوقع 4.6% | R/R 1.33 | السعر مدقق | تاريخ 4/50"
    },
    {
      "id": "ranking:ranked_opportunity:COPR:P1 — فرصة مرتبة #2",
      "level": "opportunity",
      "priority": "مراقبة قوية",
      "source": "ranking",
      "type": "ranked_opportunity",
      "symbol": "COPR",
      "title": "P1 — فرصة مرتبة #2",
      "text": "الثقة 78% | R/R 1.00 | عائد متوقع 3.1%",
      "action": "راجع سعر الدخول والوقف قبل أي قرار، والبيانات عامة ومتأخرة",
      "why": "احتمال الهدف 78% | ربح هدف1 5.6% | عائد متوقع 3.1% | R/R 1.00 | السعر مدقق | تاريخ 4/50"
    },
    {
      "id": "ranking:ranked_opportunity:ARAB:P1 — فرصة مرتبة #3",
      "level": "opportunity",
      "priority": "مراقبة قوية",
      "source": "ranking",
      "type": "ranked_opportunity",
      "symbol": "ARAB",
      "title": "P1 — فرصة مرتبة #3",
      "text": "الثقة 78% | R/R 1.00 | عائد متوقع 2.7%",
      "action": "راجع سعر الدخول والوقف قبل أي قرار، والبيانات عامة ومتأخرة",
      "why": "احتمال الهدف 78% | ربح هدف1 4.8% | عائد متوقع 2.7% | R/R 1.00 | السعر مدقق | تاريخ 4/50"
    },
    {
      "id": "ranking:p2_watch:KRDI:P2 مراقبة #6",
      "level": "watch",
      "priority": "مراقبة",
      "source": "ranking",
      "type": "p2_watch",
      "symbol": "KRDI",
      "title": "P2 مراقبة #6",
      "text": "prob=75% expected=1.47% rr=1",
      "action": "انتظار Trigger واضح",
      "why": "احتمال الهدف 75% | ربح هدف1 2.9% | عائد متوقع 1.5% | R/R 1.00 | السعر مدقق | تاريخ 4/50"
    },
    {
      "id": "ranking:p2_watch:HRHO:P2 مراقبة #7",
      "level": "watch",
      "priority": "مراقبة",
      "source": "ranking",
      "type": "p2_watch",
      "symbol": "HRHO",
      "title": "P2 مراقبة #7",
      "text": "prob=73% expected=2.46% rr=1.21",
      "action": "انتظار Trigger واضح",
      "why": "احتمال الهدف 73% | ربح هدف1 4.8% | عائد متوقع 2.5% | R/R 1.21 | السعر مدقق | تاريخ 5/50"
    },
    {
      "id": "ranking:p2_watch:DAPH:P2 مراقبة #8",
      "level": "watch",
      "priority": "مراقبة",
      "source": "ranking",
      "type": "p2_watch",
      "symbol": "DAPH",
      "title": "P2 مراقبة #8",
      "text": "prob=72% expected=1.99% rr=0.96",
      "action": "انتظار Trigger واضح",
      "why": "احتمال الهدف 72% | ربح هدف1 4.6% | عائد متوقع 2.0% | R/R 0.96 | السعر مدقق | تاريخ 4/50"
    },
    {
      "id": "ranking:p2_watch:OCDI:P2 مراقبة #9",
      "level": "watch",
      "priority": "مراقبة",
      "source": "ranking",
      "type": "p2_watch",
      "symbol": "OCDI",
      "title": "P2 مراقبة #9",
      "text": "prob=72% expected=1.9% rr=0.86",
      "action": "انتظار Trigger واضح",
      "why": "احتمال الهدف 72% | ربح هدف1 4.8% | عائد متوقع 1.9% | R/R 0.86 | السعر مدقق | تاريخ 5/50"
    },
    {
      "id": "ranking:p2_watch:RMDA:P2 مراقبة #10",
      "level": "watch",
      "priority": "مراقبة",
      "source": "ranking",
      "type": "p2_watch",
      "symbol": "RMDA",
      "title": "P2 مراقبة #10",
      "text": "prob=72% expected=1.82% rr=0.92",
      "action": "انتظار Trigger واضح",
      "why": "احتمال الهدف 72% | ربح هدف1 4.4% | عائد متوقع 1.8% | R/R 0.92 | السعر مدقق | تاريخ 5/50"
    },
    {
      "id": "ranking:p2_watch:IFAP:P2 مراقبة #11",
      "level": "watch",
      "priority": "مراقبة",
      "source": "ranking",
      "type": "p2_watch",
      "symbol": "IFAP",
      "title": "P2 مراقبة #11",
      "text": "prob=72% expected=1.56% rr=0.87",
      "action": "انتظار Trigger واضح",
      "why": "احتمال الهدف 72% | ربح هدف1 3.9% | عائد متوقع 1.6% | R/R 0.87 | السعر مدقق | تاريخ 5/50"
    },
    {
      "id": "ranking:ranked_opportunity:ROTO:P2 — فرصة مرتبة #5",
      "level": "watch",
      "priority": "مراقبة",
      "source": "ranking",
      "type": "ranked_opportunity",
      "symbol": "ROTO",
      "title": "P2 — فرصة مرتبة #5",
      "text": "الثقة 78% | R/R 0.97 | عائد متوقع 4.7%",
      "action": "راجع سعر الدخول والوقف قبل أي قرار، والبيانات عامة ومتأخرة",
      "why": "احتمال الهدف 78% | ربح هدف1 8.5% | عائد متوقع 4.7% | R/R 0.97 | السعر مدقق | تاريخ 4/50"
    },
    {
      "id": "ranking:ranked_opportunity:DOMT:P2 — فرصة مرتبة #6",
      "level": "watch",
      "priority": "مراقبة",
      "source": "ranking",
      "type": "ranked_opportunity",
      "symbol": "DOMT",
      "title": "P2 — فرصة مرتبة #6",
      "text": "الثقة 78% | R/R 0.99 | عائد متوقع 2.6%",
      "action": "راجع سعر الدخول والوقف قبل أي قرار، والبيانات عامة ومتأخرة",
      "why": "احتمال الهدف 78% | ربح هدف1 4.6% | عائد متوقع 2.6% | R/R 0.99 | السعر مدقق | تاريخ 5/50"
    },
    {
      "id": "ranking:ranked_opportunity:KRDI:P2 — فرصة مرتبة #7",
      "level": "watch",
      "priority": "مراقبة",
      "source": "ranking",
      "type": "ranked_opportunity",
      "symbol": "KRDI",
      "title": "P2 — فرصة مرتبة #7",
      "text": "الثقة 75% | R/R 1.00 | عائد متوقع 1.5%",
      "action": "راجع سعر الدخول والوقف قبل أي قرار، والبيانات عامة ومتأخرة",
      "why": "احتمال الهدف 75% | ربح هدف1 2.9% | عائد متوقع 1.5% | R/R 1.00 | السعر مدقق | تاريخ 4/50"
    },
    {
      "id": "ranking:ranked_opportunity:FAITA:P2 — فرصة مرتبة #8",
      "level": "watch",
      "priority": "مراقبة",
      "source": "ranking",
      "type": "ranked_opportunity",
      "symbol": "FAITA",
      "title": "P2 — فرصة مرتبة #8",
      "text": "الثقة 73% | R/R 1.33 | عائد متوقع 2.1%",
      "action": "راجع سعر الدخول والوقف قبل أي قرار، والبيانات عامة ومتأخرة",
      "why": "احتمال الهدف 73% | ربح هدف1 4.0% | عائد متوقع 2.1% | R/R 1.33 | السعر مدقق | تاريخ 4/50"
    },
    {
      "id": "ranking:ranked_opportunity:ETEL:P2 — فرصة مرتبة #9",
      "level": "watch",
      "priority": "مراقبة",
      "source": "ranking",
      "type": "ranked_opportunity",
      "symbol": "ETEL",
      "title": "P2 — فرصة مرتبة #9",
      "text": "الثقة 72% | R/R 0.91 | عائد متوقع 2.1%",
      "action": "راجع سعر الدخول والوقف قبل أي قرار، والبيانات عامة ومتأخرة",
      "why": "احتمال الهدف 72% | ربح هدف1 5.1% | عائد متوقع 2.1% | R/R 0.91 | السعر مدقق | تاريخ 5/50"
    },
    {
      "id": "ranking:ranked_opportunity:RMDA:P2 — فرصة مرتبة #10",
      "level": "watch",
      "priority": "مراقبة",
      "source": "ranking",
      "type": "ranked_opportunity",
      "symbol": "RMDA",
      "title": "P2 — فرصة مرتبة #10",
      "text": "الثقة 72% | R/R 1.00 | عائد متوقع 2.0%",
      "action": "راجع سعر الدخول والوقف قبل أي قرار، والبيانات عامة ومتأخرة",
      "why": "احتمال الهدف 72% | ربح هدف1 4.6% | عائد متوقع 2.0% | R/R 1.00 | السعر مدقق | تاريخ 5/50"
    },
    {
      "id": "ranking:ranked_opportunity:HRHO:P2 — فرصة مرتبة #11",
      "level": "watch",
      "priority": "مراقبة",
      "source": "ranking",
      "type": "ranked_opportunity",
      "symbol": "HRHO",
      "title": "P2 — فرصة مرتبة #11",
      "text": "الثقة 72% | R/R 1.01 | عائد متوقع 1.9%",
      "action": "راجع سعر الدخول والوقف قبل أي قرار، والبيانات عامة ومتأخرة",
      "why": "احتمال الهدف 72% | ربح هدف1 4.4% | عائد متوقع 2.0% | R/R 1.01 | السعر مدقق | تاريخ 5/50"
    },
    {
      "id": "ranking:ranked_opportunity:IFAP:P2 — فرصة مرتبة #12",
      "level": "watch",
      "priority": "مراقبة",
      "source": "ranking",
      "type": "ranked_opportunity",
      "symbol": "IFAP",
      "title": "P2 — فرصة مرتبة #12",
      "text": "الثقة 72% | R/R 1.01 | عائد متوقع 1.9%",
      "action": "راجع سعر الدخول والوقف قبل أي قرار، والبيانات عامة ومتأخرة",
      "why": "احتمال الهدف 72% | ربح هدف1 4.2% | عائد متوقع 1.9% | R/R 1.01 | السعر مدقق | تاريخ 5/50"
    },
    {
      "id": "news:news_linking_low:market:الأخبار موجودة لكن ربطها بالأسهم محدود",
      "level": "info",
      "priority": "معلومة",
      "source": "news",
      "type": "news_linking_low",
      "symbol": null,
      "title": "الأخبار موجودة لكن ربطها بالأسهم محدود",
      "text": "أخبار مصنفة: 160 | رموز مرتبطة: 7",
      "action": "تحسين قاموس ربط الأخبار بالرموز والقطاعات في مرحلة لاحقة",
      "why": "وجود أخبار كثيرة لا يعني تأثيرًا مباشرًا على كل سهم"
    },
    {
      "id": "system:suppressed_alerts_summary",
      "level": "info",
      "priority": "معلومة",
      "source": "system",
      "type": "suppressed_summary",
      "symbol": null,
      "title": "تم إخفاء تنبيهات منخفضة الأولوية لتقليل الضوضاء",
      "text": "مخفي: مهم 131 / فرص 6 / مراقبة 0 / معلومات 0",
      "action": "استخدم التقارير التفصيلية عند الحاجة",
      "why": "مركز التنبيهات يعرض المهم فقط حتى لا يتحول إلى قائمة مزعجة"
    }
  ],
  "note": "Calibrated: critical only for true blocking conflicts; stale prices are summarized, low-priority alerts are capped."
}