{
  "ok": true,
  "engine": "v8_9_3_executive_home",
  "generatedAt": "2026-07-05T17:32:23.063Z",
  "summary": {
    "dataStatus": "ok",
    "coveragePct": 93.8,
    "marketRows": 210,
    "source": "mubasher_symbol_pages_precise_enriched",
    "actionableCount": 217,
    "aPlus": 1,
    "aOrBetter": 6,
    "criticalAlerts": 8,
    "historyAverage": 4,
    "historyComplete50": 0,
    "recommendationIndex": 62.6,
    "recommendationGrade": "متوسط",
    "enginesOk": 9,
    "enginesWarn": 3
  },
  "topOpportunities": [
    {
      "rank": 77,
      "symbol": "TYCN",
      "name": "تايكون القابضة",
      "tier": "C",
      "decision": "انتظار تأكيد",
      "recommendation": "تجنب / مخاطر عالية",
      "compositeScore": 0,
      "confidence": 100,
      "dataQualityScore": 100,
      "technicalScore": 27.8,
      "liquidityScore": 70,
      "financialScore": 55,
      "newsScore": 52,
      "historySessions": 4,
      "price": 27.4,
      "priceDisplay": "27.4",
      "changePct": -10.1,
      "turnover": 103780592,
      "volume": 3603158,
      "support1": 28.11,
      "resistance1": 33.05,
      "entryLow": -9.91,
      "entryHigh": 27.79,
      "entryRange": "-9.91 - 27.79",
      "target1": 33.05,
      "target2": 35.49,
      "stopLoss": 27.41,
      "riskReward": 13.93,
      "priceState": "inside_entry",
      "precisionRisk": false,
      "executionAllowed": false,
      "blocks": [
        "limited_history"
      ],
      "reason": "تحت Pivot + ضغط سعري سلبي + سيولة قوية + كسر دعم + مساحة قبل المقاومة | لا يوجد سجل تاريخي كافٍ (3/50) | Snapshot evidence: 141 observations / 3 dates, score 86%. ليس 50 جلسة. | موجود في محرك الأولويات | موجود في التوصيات اليومية | سيولة قوية | عائد/مخاطرة مقبول | السعر داخل نطاق الدخول | تاريخ محدود 4/50",
      "decisionNote": "مشترك بين الفرص اليومية ومحرك الأولويات | داخل نطاق الدخول | تاريخ محدود 4/50 | R/R جيد",
      "sourceUrl": "https://english.mubasher.info/markets/EGX/stocks/TYCN/"
    },
    {
      "rank": 78,
      "symbol": "TAQA",
      "name": "طاقة عربية",
      "tier": "C",
      "decision": "انتظار تأكيد",
      "recommendation": "تجنب / مخاطر عالية",
      "compositeScore": 0,
      "confidence": 100,
      "dataQualityScore": 100,
      "technicalScore": 25.6,
      "liquidityScore": 45,
      "financialScore": 55,
      "newsScore": 52,
      "historySessions": 4,
      "price": 14.5,
      "priceDisplay": "14.5",
      "changePct": -1.22,
      "turnover": 24160568,
      "volume": 1654388,
      "support1": 14.59,
      "resistance1": 14.86,
      "entryLow": -1.5,
      "entryHigh": 14.6,
      "entryRange": "-1.5 - 14.6",
      "target1": 14.86,
      "target2": 15.01,
      "stopLoss": 14.23,
      "riskReward": 0.67,
      "priceState": "inside_entry",
      "precisionRisk": false,
      "executionAllowed": false,
      "blocks": [
        "weak_rr",
        "limited_history"
      ],
      "reason": "تحت Pivot + ضغط سعري سلبي + سيولة مقبولة + كسر دعم | لا يوجد سجل تاريخي كافٍ (3/50) | Snapshot evidence: 163 observations / 3 dates, score 86%. ليس 50 جلسة. | موجود في محرك الأولويات | موجود في التوصيات اليومية | السعر داخل نطاق الدخول | تاريخ محدود 4/50",
      "decisionNote": "مشترك بين الفرص اليومية ومحرك الأولويات | داخل نطاق الدخول | تاريخ محدود 4/50",
      "sourceUrl": "https://english.mubasher.info/markets/EGX/stocks/TAQA/"
    },
    {
      "rank": 79,
      "symbol": "WCDF",
      "name": "مطاحن وسط وغرب الدلتا",
      "tier": "C",
      "decision": "انتظار تأكيد",
      "recommendation": "تجنب / مخاطر عالية",
      "compositeScore": 0,
      "confidence": 100,
      "dataQualityScore": 100,
      "technicalScore": 30,
      "liquidityScore": 12,
      "financialScore": 55,
      "newsScore": 52,
      "historySessions": 4,
      "price": 506.06,
      "priceDisplay": "506.06",
      "changePct": -2.31,
      "turnover": 1427213.63,
      "volume": 2799,
      "support1": 510.37,
      "resistance1": 532.37,
      "entryLow": -2.79,
      "entryHigh": 511.12,
      "entryRange": "-2.79 - 511.12",
      "target1": 532.37,
      "target2": 546.68,
      "stopLoss": 497.61,
      "riskReward": 1.57,
      "priceState": "inside_entry",
      "precisionRisk": false,
      "executionAllowed": false,
      "blocks": [
        "limited_history"
      ],
      "reason": "تحت Pivot + ضغط سعري سلبي + سيولة ضعيفة + كسر دعم + مساحة قبل المقاومة | لا يوجد سجل تاريخي كافٍ (3/50) | Snapshot evidence: 153 observations / 3 dates, score 84%. ليس 50 جلسة. | موجود في محرك الأولويات | موجود في التوصيات اليومية | عائد/مخاطرة مقبول | السعر داخل نطاق الدخول | تاريخ محدود 4/50",
      "decisionNote": "مشترك بين الفرص اليومية ومحرك الأولويات | داخل نطاق الدخول | تاريخ محدود 4/50 | R/R جيد",
      "sourceUrl": "https://english.mubasher.info/markets/EGX/stocks/WCDF/"
    },
    {
      "rank": 80,
      "symbol": "DCCC",
      "name": "دمياط لتداول الحاويات",
      "tier": "C",
      "decision": "انتظار تأكيد",
      "recommendation": "تجنب / مخاطر عالية",
      "compositeScore": 0,
      "confidence": 100,
      "dataQualityScore": 100,
      "technicalScore": 44.6,
      "liquidityScore": 12,
      "financialScore": 55,
      "newsScore": 52,
      "historySessions": 4,
      "price": 9.35,
      "priceDisplay": "9.35",
      "changePct": 4.94,
      "turnover": 916.3,
      "volume": 98,
      "support1": -10.44,
      "resistance1": -10.02,
      "entryLow": -189.83,
      "entryHigh": 9.44,
      "entryRange": "-189.83 - 9.44",
      "target1": 9.77,
      "target2": 10.31,
      "stopLoss": -10.18,
      "riskReward": 0.02,
      "priceState": "inside_entry",
      "precisionRisk": false,
      "executionAllowed": false,
      "blocks": [
        "weak_rr",
        "limited_history"
      ],
      "reason": "تحت Pivot + السعر إيجابي + سيولة ضعيفة + كسر دعم | لا يوجد سجل تاريخي كافٍ (3/50) | Snapshot evidence: 150 observations / 3 dates, score 84%. ليس 50 جلسة. | موجود في محرك الأولويات | موجود في التوصيات اليومية | السعر داخل نطاق الدخول | تاريخ محدود 4/50",
      "decisionNote": "مشترك بين الفرص اليومية ومحرك الأولويات | داخل نطاق الدخول | تاريخ محدود 4/50",
      "sourceUrl": "https://english.mubasher.info/markets/EGX/stocks/DCCC/"
    },
    {
      "rank": 81,
      "symbol": "CPME",
      "name": "كاتاليست بارتنرز",
      "tier": "C",
      "decision": "انتظار تأكيد",
      "recommendation": "تجنب / مخاطر عالية",
      "compositeScore": 0,
      "confidence": 100,
      "dataQualityScore": 100,
      "technicalScore": 27.8,
      "liquidityScore": 12,
      "financialScore": 55,
      "newsScore": 52,
      "historySessions": 4,
      "price": 18,
      "priceDisplay": "18",
      "changePct": -6.49,
      "turnover": 1419177.88,
      "volume": 78440,
      "support1": 19.02,
      "resistance1": 19.37,
      "entryLow": -5.89,
      "entryHigh": 18.18,
      "entryRange": "-5.89 - 18.18",
      "target1": 19.37,
      "target2": 19.48,
      "stopLoss": 18.54,
      "riskReward": 11900,
      "priceState": "inside_entry",
      "precisionRisk": false,
      "executionAllowed": false,
      "blocks": [
        "limited_history"
      ],
      "reason": "تحت Pivot + ضغط سعري سلبي + سيولة ضعيفة + كسر دعم + مساحة قبل المقاومة | لا يوجد سجل تاريخي كافٍ (3/50) | Snapshot evidence: 150 observations / 3 dates, score 84%. ليس 50 جلسة. | موجود في محرك الأولويات | موجود في التوصيات اليومية | عائد/مخاطرة مقبول | السعر داخل نطاق الدخول | تاريخ محدود 4/50",
      "decisionNote": "مشترك بين الفرص اليومية ومحرك الأولويات | داخل نطاق الدخول | تاريخ محدود 4/50 | R/R جيد",
      "sourceUrl": "https://english.mubasher.info/markets/EGX/stocks/CPME/"
    },
    {
      "rank": 82,
      "symbol": "ELNA",
      "name": "النصر لتصنيع الحاصلات الزراعية",
      "tier": "C",
      "decision": "انتظار تأكيد",
      "recommendation": "تجنب / مخاطر عالية",
      "compositeScore": 0,
      "confidence": 100,
      "dataQualityScore": 100,
      "technicalScore": 32.7,
      "liquidityScore": 12,
      "financialScore": 55,
      "newsScore": 52,
      "historySessions": 2,
      "price": 37.81,
      "priceDisplay": "37.81",
      "changePct": 0,
      "turnover": 230773.63,
      "volume": 5969,
      "support1": 36.66,
      "resistance1": 38.39,
      "entryLow": 36.66,
      "entryHigh": 37.24,
      "entryRange": "36.66 - 37.24",
      "target1": 38.39,
      "target2": 38.98,
      "stopLoss": 35.52,
      "riskReward": 0.67,
      "priceState": "near_entry",
      "precisionRisk": false,
      "executionAllowed": false,
      "blocks": [
        "weak_rr",
        "limited_history"
      ],
      "reason": "تحت Pivot + سيولة ضعيفة + كسر دعم | لا يوجد سجل تاريخي كافٍ (2/50) | Snapshot evidence: 36 observations / 2 dates, score 70%. ليس 50 جلسة. | موجود في محرك الأولويات | موجود في التوصيات اليومية | السعر قريب من نطاق الدخول | تاريخ محدود 2/50",
      "decisionNote": "مشترك بين الفرص اليومية ومحرك الأولويات | قريب من الدخول | تاريخ محدود 2/50",
      "sourceUrl": "https://english.mubasher.info/markets/EGX/stocks/ELNA/"
    },
    {
      "rank": 193,
      "symbol": "CRST",
      "name": "كريست مارك",
      "tier": "Risk",
      "decision": "تجنب / مراجعة",
      "recommendation": "تجنب / مخاطر عالية",
      "compositeScore": 0,
      "confidence": 100,
      "dataQualityScore": 100,
      "technicalScore": 37.4,
      "liquidityScore": 61,
      "financialScore": 55,
      "newsScore": 52,
      "historySessions": 4,
      "price": 1.36,
      "priceDisplay": "1.36",
      "changePct": -2.99,
      "turnover": 55806496,
      "volume": 41748692,
      "support1": 1.31,
      "resistance1": 1.37,
      "entryLow": -3.45,
      "entryHigh": 1.33,
      "entryRange": "-3.45 - 1.33",
      "target1": 1.37,
      "target2": 1.41,
      "stopLoss": 1.28,
      "riskReward": 0.66,
      "priceState": "near_entry",
      "precisionRisk": false,
      "executionAllowed": false,
      "blocks": [
        "price_mismatch",
        "weak_rr",
        "limited_history"
      ],
      "reason": "تحت Pivot + ضغط سعري سلبي + سيولة مقبولة + قريب من دعم | لا يوجد سجل تاريخي كافٍ (3/50) | Snapshot evidence: 141 observations / 3 dates, score 86%. ليس 50 جلسة. | موجود في محرك الأولويات | موجود في التوصيات اليومية | السعر قريب من نطاق الدخول | تاريخ محدود 4/50 | يوجد فرق سعر يحتاج مراجعة",
      "decisionNote": "مشترك بين الفرص اليومية ومحرك الأولويات | قريب من الدخول | تاريخ محدود 4/50",
      "sourceUrl": "https://english.mubasher.info/markets/EGX/stocks/CRST/"
    },
    {
      "rank": 194,
      "symbol": "AIDC",
      "name": "العربية للاستثمار والتنمية",
      "tier": "Risk",
      "decision": "انتظار تحقق السعر",
      "recommendation": "انتظار تحقق السعر",
      "compositeScore": 0,
      "confidence": 100,
      "dataQualityScore": 100,
      "technicalScore": 35.1,
      "liquidityScore": 50,
      "financialScore": 55,
      "newsScore": 52,
      "historySessions": 4,
      "price": 0.66,
      "priceDisplay": "0.660",
      "changePct": -0.6,
      "turnover": 21007102,
      "volume": 31229358,
      "support1": 0.61,
      "resistance1": 0.72,
      "entryLow": 0.65,
      "entryHigh": 0.68,
      "entryRange": "0.65 - 0.68",
      "target1": 0.72,
      "target2": 0.76,
      "stopLoss": 0.59,
      "riskReward": 0.53,
      "priceState": "precision_risk",
      "precisionRisk": true,
      "executionAllowed": false,
      "blocks": [
        "price_mismatch",
        "price_precision_risk",
        "weak_rr",
        "limited_history"
      ],
      "reason": "تحت Pivot + سيولة مقبولة + مساحة قبل المقاومة | لا يوجد سجل تاريخي كافٍ (3/50) | Snapshot evidence: 141 observations / 3 dates, score 86%. ليس 50 جلسة. | موجود في محرك الأولويات | موجود في التوصيات اليومية | السعر أقل من 1 جنيه ويحتاج تأكيد 3 خانات قبل أي توصية تنفيذية | السعر داخل نطاق الدخول | تاريخ محدود 4/50 | يوجد فرق سعر يحتاج مراجعة",
      "decisionNote": "لا تنفيذ: السعر يحتاج تأكيد 3 خانات | مشترك بين الفرص اليومية ومحرك الأولويات | تاريخ محدود 4/50",
      "sourceUrl": "https://english.mubasher.info/markets/EGX/stocks/AIDC/"
    },
    {
      "rank": 195,
      "symbol": "GGCC",
      "name": "الجيزة العامة للمقاولات",
      "tier": "Risk",
      "decision": "انتظار تحقق السعر",
      "recommendation": "انتظار تحقق السعر",
      "compositeScore": 0,
      "confidence": 100,
      "dataQualityScore": 100,
      "technicalScore": 33.4,
      "liquidityScore": 50,
      "financialScore": 55,
      "newsScore": 52,
      "historySessions": 4,
      "price": 0.52,
      "priceDisplay": "0.520",
      "changePct": 1.24,
      "turnover": 26574294,
      "volume": 54452263,
      "support1": 0.47,
      "resistance1": 0.49,
      "entryLow": 0.48,
      "entryHigh": 0.49,
      "entryRange": "0.48 - 0.49",
      "target1": 0.51,
      "target2": 0.54,
      "stopLoss": 0.46,
      "riskReward": 1,
      "priceState": "precision_risk",
      "precisionRisk": true,
      "executionAllowed": false,
      "blocks": [
        "price_mismatch",
        "price_precision_risk",
        "weak_rr",
        "extended_price",
        "limited_history"
      ],
      "reason": "تحت Pivot + السعر إيجابي + سيولة مقبولة + قريب جدًا من المقاومة | لا يوجد سجل تاريخي كافٍ (3/50) | Snapshot evidence: 141 observations / 3 dates, score 86%. ليس 50 جلسة. | موجود في محرك الأولويات | موجود في التوصيات اليومية | السعر أقل من 1 جنيه ويحتاج تأكيد 3 خانات قبل أي توصية تنفيذية | السعر ابتعد عن نقطة الدخول | تاريخ محدود 4/50 | يوجد فرق سعر يحتاج مراجعة",
      "decisionNote": "لا تنفيذ: السعر يحتاج تأكيد 3 خانات | مشترك بين الفرص اليومية ومحرك الأولويات | تاريخ محدود 4/50",
      "sourceUrl": "https://english.mubasher.info/markets/EGX/stocks/GGCC/"
    },
    {
      "rank": 196,
      "symbol": "ARAB",
      "name": "المطورون العرب القابضة",
      "tier": "Risk",
      "decision": "انتظار تحقق السعر",
      "recommendation": "انتظار تحقق السعر",
      "compositeScore": 0,
      "confidence": 100,
      "dataQualityScore": 100,
      "technicalScore": 28.6,
      "liquidityScore": 50,
      "financialScore": 55,
      "newsScore": 52,
      "historySessions": 4,
      "price": 0.21,
      "priceDisplay": "0.210",
      "changePct": -1.89,
      "turnover": 42145176,
      "volume": 201126446,
      "support1": 0.21,
      "resistance1": 0.21,
      "entryLow": 0.21,
      "entryHigh": 0.21,
      "entryRange": "0.21 - 0.21",
      "target1": 0.22,
      "target2": 0.23,
      "stopLoss": 0.2,
      "riskReward": 1.15,
      "priceState": "precision_risk",
      "precisionRisk": true,
      "executionAllowed": false,
      "blocks": [
        "price_precision_risk",
        "limited_history"
      ],
      "reason": "تحت Pivot + ضغط سعري سلبي + سيولة مقبولة + قريب من دعم + قريب جدًا من المقاومة | لا يوجد سجل تاريخي كافٍ (3/50) | Snapshot evidence: 153 observations / 3 dates, score 85%. ليس 50 جلسة. | موجود في محرك الأولويات | موجود في التوصيات اليومية | السعر أقل من 1 جنيه ويحتاج تأكيد 3 خانات قبل أي توصية تنفيذية | السعر داخل نطاق الدخول | تاريخ محدود 4/50",
      "decisionNote": "لا تنفيذ: السعر يحتاج تأكيد 3 خانات | مشترك بين الفرص اليومية ومحرك الأولويات | تاريخ محدود 4/50",
      "sourceUrl": "https://english.mubasher.info/markets/EGX/stocks/ARAB/"
    }
  ],
  "criticalAlerts": [
    {
      "id": "price:price_conflict:ABUK:تعارض سعر",
      "level": "critical",
      "priority": "عاجل",
      "source": "price",
      "type": "price_conflict",
      "symbol": "ABUK",
      "title": "تعارض سعر",
      "text": "final=69.7, recommendation=67.94, market=69.7, cache=67.94",
      "action": "مراجعة السعر قبل أي قرار قوي",
      "why": "max/min internal price spread 2.59%"
    },
    {
      "id": "price:price_conflict:ACAMD:تعارض سعر",
      "level": "critical",
      "priority": "عاجل",
      "source": "price",
      "type": "price_conflict",
      "symbol": "ACAMD",
      "title": "تعارض سعر",
      "text": "final=2.3, recommendation=2.25, market=2.3, cache=2.25",
      "action": "مراجعة السعر قبل أي قرار قوي",
      "why": "max/min internal price spread 2.22%"
    },
    {
      "id": "price:price_conflict:ACGC:تعارض سعر",
      "level": "critical",
      "priority": "عاجل",
      "source": "price",
      "type": "price_conflict",
      "symbol": "ACGC",
      "title": "تعارض سعر",
      "text": "final=9.33, recommendation=9.23, market=9.33, cache=9.23",
      "action": "مراجعة السعر قبل أي قرار قوي",
      "why": "max/min internal price spread 1.08%"
    },
    {
      "id": "price:price_conflict:ADCI:تعارض سعر",
      "level": "critical",
      "priority": "عاجل",
      "source": "price",
      "type": "price_conflict",
      "symbol": "ADCI",
      "title": "تعارض سعر",
      "text": "final=238.5, recommendation=240.97, market=238.5, cache=240.97",
      "action": "مراجعة السعر قبل أي قرار قوي",
      "why": "max/min internal price spread 1.04%"
    },
    {
      "id": "price:price_conflict:AFMC:تعارض سعر",
      "level": "critical",
      "priority": "عاجل",
      "source": "price",
      "type": "price_conflict",
      "symbol": "AFMC",
      "title": "تعارض سعر",
      "text": "final=71.2, recommendation=69.44, market=71.2, cache=69.44",
      "action": "مراجعة السعر قبل أي قرار قوي",
      "why": "max/min internal price spread 2.53%"
    },
    {
      "id": "price:price_conflict:AIDC:تعارض سعر",
      "level": "critical",
      "priority": "عاجل",
      "source": "price",
      "type": "price_conflict",
      "symbol": "AIDC",
      "title": "تعارض سعر",
      "text": "final=0.66, recommendation=0.67, market=0.66, cache=0.67",
      "action": "مراجعة السعر قبل أي قرار قوي",
      "why": "max/min internal price spread 1.52%"
    },
    {
      "id": "price:price_conflict:ALUM:تعارض سعر",
      "level": "critical",
      "priority": "عاجل",
      "source": "price",
      "type": "price_conflict",
      "symbol": "ALUM",
      "title": "تعارض سعر",
      "text": "final=21.85, recommendation=21.45, market=21.85, cache=21.45",
      "action": "مراجعة السعر قبل أي قرار قوي",
      "why": "max/min internal price spread 1.86%"
    },
    {
      "id": "price:price_conflict:AMER:تعارض سعر",
      "level": "critical",
      "priority": "عاجل",
      "source": "price",
      "type": "price_conflict",
      "symbol": "AMER",
      "title": "تعارض سعر",
      "text": "final=2.46, recommendation=2.42, market=2.46, cache=2.42",
      "action": "مراجعة السعر قبل أي قرار قوي",
      "why": "max/min internal price spread 1.65%"
    }
  ],
  "nextActions": [
    "ابدأ بالتنبيهات الحرجة قبل الفرص الجديدة.",
    "راجع أسهم A+/A فقط داخل نطاق الدخول وبوقف خسارة واضح.",
    "تعامل مع نقص 50 جلسة كنقص تحليل تاريخي وليس فشل تشغيل."
  ],
  "disclaimer": "مساعد قرار وتحليل فقط. لا يوجد ضمان ربح أو أمر تداول."
}
