{
  "ok": true,
  "engine": "v7_4_git_date_recovery_fix",
  "generatedAt": "2026-07-02T22:42:22.579Z",
  "commitsScanned": 34,
  "filesScanned": 90,
  "snapshotsRecovered": 70,
  "rowsRecovered": 10996,
  "symbolsRecovered": 209,
  "uniqueSessionDatesRecovered": 2,
  "symbolsWithComplete50AfterRecovery": 0,
  "averageSessionsAfterRecovery": 2,
  "dateRule": "Git commit date is used as recovered session date by default to avoid repeated generatedAt collapsing history.",
  "message": "Recovered 10996 rows from 70 repository snapshots across 2 unique Git dates.",
  "recoveredBySymbol": {
    "HRHO": 69,
    "AMER": 59,
    "MFPC": 69,
    "CCAP": 69,
    "ETEL": 69,
    "SWDY": 69,
    "TMGH": 69,
    "ABUK": 69,
    "ORAS": 69,
    "ORHD": 69,
    "FWRY": 69,
    "COMI": 69,
    "EGAL": 69,
    "EAST": 69,
    "NIPH": 68,
    "RMDA": 68,
    "POUL": 68,
    "LCSW": 58,
    "EXPA": 68,
    "CIRA": 68,
    "MASR": 66,
    "RAYA": 68,
    "AXPH": 58,
    "AMOC": 68,
    "DOMT": 58,
    "IFAP": 68,
    "BTFH": 68,
    "EASB": 46,
    "PHDC": 68,
    "HELI": 68,
    "KABO": 58,
    "CLHO": 68,
    "ADIB": 68,
    "EGBE": 68,
    "CICH": 68,
    "SUGR": 58,
    "SPIN": 58,
    "ADRI": 7,
    "IRON": 68,
    "ESRS": 7,
    "ELWA": 55,
    "EFID": 68,
    "OLFI": 68,
    "EGCH": 68,
    "ARCC": 68,
    "MCQE": 68,
    "JUFO": 68,
    "MICH": 58,
    "ISPH": 68,
    "SKPC": 68,
    "SAUD": 68,
    "OCDI": 67,
    "HDBK": 67,
    "EGTS": 67,
    "ACAMD": 57,
    "CIEB": 67,
    "CNFN": 57,
    "FAIT": 67,
    "ACGC": 57,
    "AIFI": 6,
    "CANA": 67,
    "GBCO": 67,
    "ALCN": 67,
    "ISMQ": 61,
    "BONY": 61,
    "PRDC": 61,
    "MTIE": 61,
    "EFIH": 61,
    "VLMRA": 61,
    "SCEM": 61,
    "UBEE": 61,
    "SCTS": 61,
    "QNBE": 61,
    "EMFD": 61,
    "PHAR": 61,
    "MHOT": 61,
    "TALM": 61,
    "FAITA": 61,
    "EFIC": 61,
    "MBSC": 61,
    "ATQA": 61,
    "VLMR": 61,
    "FERC": 61,
    "VALU": 61,
    "TAQA": 61,
    "ORWE": 61,
    "MOIL": 61,
    "BINV": 61,
    "CSAG": 61,
    "SVCE": 51,
    "MPCI": 51,
    "PRCL": 51,
    "ZEOT": 51,
    "EHDR": 51,
    "ZMID": 51,
    "KORA": 51,
    "UEFM": 51,
    "DAPH": 51,
    "RACC": 51,
    "MFSC": 51,
    "INFI": 51,
    "OIH": 51,
    "BIOC": 51,
    "MPCO": 51,
    "MPRC": 51,
    "ELEC": 51,
    "ELKA": 51,
    "ETRS": 51,
    "ATLC": 51,
    "DSCW": 51,
    "ELSH": 51,
    "AMIA": 51,
    "ASCM": 51,
    "PHGC": 51,
    "OCPH": 51,
    "OFH": 51,
    "GGRN": 51,
    "PHTV": 51,
    "CPCI": 51,
    "GSSC": 51,
    "SDTI": 51,
    "KZPC": 51,
    "EALR": 51,
    "GPIM": 51,
    "ECAP": 51,
    "ADPC": 51,
    "EGAS": 51,
    "GDWA": 51,
    "AFMC": 51,
    "SMFR": 51,
    "ARAB": 51,
    "MIPH": 51,
    "AMES": 51,
    "MOIN": 51,
    "ACAP": 51,
    "NAPR": 51,
    "NINH": 51,
    "ENGC": 51,
    "WCDF": 51,
    "AJWA": 51,
    "UNIT": 51,
    "ADCI": 51,
    "ISMA": 51,
    "SNFC": 51,
    "NARE": 51,
    "CCRS": 48,
    "EPPK": 48,
    "COPR": 48,
    "DGTZ": 48,
    "GRCA": 48,
    "EPCO": 48,
    "GIHD": 48,
    "DCCC": 48,
    "NEDA": 48,
    "GMCI": 48,
    "CPME": 48,
    "MENA": 42,
    "RUBX": 39,
    "DTPP": 39,
    "OBRI": 39,
    "TANM": 39,
    "ARVA": 39,
    "NHPS": 39,
    "COSG": 39,
    "AREH": 39,
    "NCCW": 39,
    "MCRO": 39,
    "IDRE": 39,
    "GTWL": 39,
    "SIPC": 39,
    "AALR": 39,
    "SEIG": 39,
    "APSW": 39,
    "EBSC": 39,
    "PRMH": 39,
    "KRDI": 39,
    "AIHC": 39,
    "EEII": 39,
    "MEPA": 39,
    "ODIN": 39,
    "UEGC": 39,
    "CERA": 39,
    "MAAL": 39,
    "MILS": 39,
    "AIDC": 39,
    "CEFM": 39,
    "ALUM": 39,
    "MEGM": 39,
    "GGCC": 39,
    "ROTO": 39,
    "SPMD": 39,
    "WKOL": 39,
    "RREI": 39,
    "RTVC": 39,
    "ASPI": 39,
    "MOSC": 39,
    "TYCN": 39,
    "CRST": 39,
    "DEIN": 39,
    "SCFM": 39,
    "CAED": 39,
    "ICID": 39,
    "AFDI": 39,
    "LUTS": 39,
    "GTEX": 39,
    "UNIP": 39,
    "MOED": 39,
    "KWIN": 39,
    "SEIGA": 39
  },
  "fileDateStats": {
    "2026-07-02": 36
  }
}