{
  "ok": true,
  "engine": "v9_2_price_freshness",
  "generatedAt": "2026-07-21T14:36:17.399Z",
  "lastSourceUpdate": "2026-07-21T14:24:27.877Z",
  "sourceAgeMinutes": 11.8,
  "staleRows": [
    {
      "symbol": "MHOT",
      "issue": "recommendation price differs from market",
      "recommendationPrice": 33.98,
      "sourcePrice": 16.57,
      "diffPct": 105.07,
      "detail": "recommendations=33.98, market=16.57"
    },
    {
      "symbol": "HDBK",
      "issue": "recommendation price differs from market",
      "recommendationPrice": 166.67,
      "sourcePrice": 82.84,
      "diffPct": 101.2,
      "detail": "recommendations=166.67, market=82.84"
    },
    {
      "symbol": "AMES",
      "issue": "recommendation price differs from market",
      "recommendationPrice": 60.51,
      "sourcePrice": 107.94,
      "diffPct": -43.94,
      "detail": "recommendations=60.51, market=107.94"
    },
    {
      "symbol": "AMER",
      "issue": "recommendation price differs from market",
      "recommendationPrice": 2.42,
      "sourcePrice": 4.25,
      "diffPct": -43.06,
      "detail": "recommendations=2.42, market=4.25"
    },
    {
      "symbol": "GGCC",
      "issue": "recommendation price differs from market",
      "recommendationPrice": 0.49,
      "sourcePrice": 0.84,
      "diffPct": -41.67,
      "detail": "recommendations=0.49, market=0.84"
    },
    {
      "symbol": "UEGC",
      "issue": "recommendation price differs from market",
      "recommendationPrice": 1.45,
      "sourcePrice": 2.41,
      "diffPct": -39.83,
      "detail": "recommendations=1.45, market=2.41"
    },
    {
      "symbol": "CAED",
      "issue": "recommendation price differs from market",
      "recommendationPrice": 71.33,
      "sourcePrice": 116.02,
      "diffPct": -38.52,
      "detail": "recommendations=71.33, market=116.02"
    },
    {
      "symbol": "BIOC",
      "issue": "recommendation price differs from market",
      "recommendationPrice": 71.48,
      "sourcePrice": 109.85,
      "diffPct": -34.93,
      "detail": "recommendations=71.48, market=109.85"
    },
    {
      "symbol": "ELKA",
      "issue": "recommendation price differs from market",
      "recommendationPrice": 1.36,
      "sourcePrice": 2.06,
      "diffPct": -33.98,
      "detail": "recommendations=1.36, market=2.06"
    },
    {
      "symbol": "KWIN",
      "issue": "recommendation price differs from market",
      "recommendationPrice": 67.44,
      "sourcePrice": 99.02,
      "diffPct": -31.89,
      "detail": "recommendations=67.44, market=99.02"
    },
    {
      "symbol": "AFMC",
      "issue": "recommendation price differs from market",
      "recommendationPrice": 69.44,
      "sourcePrice": 100.74,
      "diffPct": -31.07,
      "detail": "recommendations=69.44, market=100.74"
    },
    {
      "symbol": "UNIT",
      "issue": "recommendation price differs from market",
      "recommendationPrice": 12.95,
      "sourcePrice": 18.5,
      "diffPct": -30,
      "detail": "recommendations=12.95, market=18.5"
    },
    {
      "symbol": "TYCN",
      "issue": "recommendation price differs from market",
      "recommendationPrice": 27.51,
      "sourcePrice": 21.23,
      "diffPct": 29.58,
      "detail": "recommendations=27.51, market=21.23"
    },
    {
      "symbol": "GIHD",
      "issue": "recommendation price differs from market",
      "recommendationPrice": 42.06,
      "sourcePrice": 57.25,
      "diffPct": -26.53,
      "detail": "recommendations=42.06, market=57.25"
    },
    {
      "symbol": "KABO",
      "issue": "recommendation price differs from market",
      "recommendationPrice": 6.33,
      "sourcePrice": 8.55,
      "diffPct": -25.96,
      "detail": "recommendations=6.33, market=8.55"
    },
    {
      "symbol": "GTEX",
      "issue": "recommendation price differs from market",
      "recommendationPrice": 0.03,
      "sourcePrice": 0.04,
      "diffPct": -25,
      "detail": "recommendations=0.03, market=0.04"
    },
    {
      "symbol": "NHPS",
      "issue": "recommendation price differs from market",
      "recommendationPrice": 68,
      "sourcePrice": 90.52,
      "diffPct": -24.88,
      "detail": "recommendations=68, market=90.52"
    },
    {
      "symbol": "CRST",
      "issue": "recommendation price differs from market",
      "recommendationPrice": 1.32,
      "sourcePrice": 1.73,
      "diffPct": -23.7,
      "detail": "recommendations=1.32, market=1.73"
    },
    {
      "symbol": "NARE",
      "issue": "recommendation price differs from market",
      "recommendationPrice": 13.9,
      "sourcePrice": 18.2,
      "diffPct": -23.63,
      "detail": "recommendations=13.9, market=18.2"
    },
    {
      "symbol": "HELI",
      "issue": "recommendation price differs from market",
      "recommendationPrice": 6.43,
      "sourcePrice": 8.35,
      "diffPct": -22.99,
      "detail": "recommendations=6.43, market=8.35"
    },
    {
      "symbol": "MILS",
      "issue": "recommendation price differs from market",
      "recommendationPrice": 129.64,
      "sourcePrice": 168.23,
      "diffPct": -22.94,
      "detail": "recommendations=129.64, market=168.23"
    },
    {
      "symbol": "OCPH",
      "issue": "recommendation price differs from market",
      "recommendationPrice": 356.52,
      "sourcePrice": 457.33,
      "diffPct": -22.04,
      "detail": "recommendations=356.52, market=457.33"
    },
    {
      "symbol": "UNIP",
      "issue": "recommendation price differs from market",
      "recommendationPrice": 0.33,
      "sourcePrice": 0.42,
      "diffPct": -21.43,
      "detail": "recommendations=0.33, market=0.42"
    },
    {
      "symbol": "MEPA",
      "issue": "recommendation price differs from market",
      "recommendationPrice": 1.57,
      "sourcePrice": 1.99,
      "diffPct": -21.11,
      "detail": "recommendations=1.57, market=1.99"
    },
    {
      "symbol": "SEIG",
      "issue": "recommendation price differs from market",
      "recommendationPrice": 190.54,
      "sourcePrice": 241.46,
      "diffPct": -21.09,
      "detail": "recommendations=190.54, market=241.46"
    },
    {
      "symbol": "NIPH",
      "issue": "recommendation price differs from market",
      "recommendationPrice": 180.06,
      "sourcePrice": 228.11,
      "diffPct": -21.06,
      "detail": "recommendations=180.06, market=228.11"
    },
    {
      "symbol": "PRDC",
      "issue": "recommendation price differs from market",
      "recommendationPrice": 7.7,
      "sourcePrice": 9.71,
      "diffPct": -20.7,
      "detail": "recommendations=7.7, market=9.71"
    },
    {
      "symbol": "CEFM",
      "issue": "recommendation price differs from market",
      "recommendationPrice": 100.07,
      "sourcePrice": 125.12,
      "diffPct": -20.02,
      "detail": "recommendations=100.07, market=125.12"
    },
    {
      "symbol": "EPCO",
      "issue": "recommendation price differs from market",
      "recommendationPrice": 8.7,
      "sourcePrice": 10.74,
      "diffPct": -18.99,
      "detail": "recommendations=8.7, market=10.74"
    },
    {
      "symbol": "GRCA",
      "issue": "recommendation price differs from market",
      "recommendationPrice": 52.29,
      "sourcePrice": 64.1,
      "diffPct": -18.42,
      "detail": "recommendations=52.29, market=64.1"
    },
    {
      "symbol": "SCEM",
      "issue": "recommendation price differs from market",
      "recommendationPrice": 63.32,
      "sourcePrice": 77.19,
      "diffPct": -17.97,
      "detail": "recommendations=63.32, market=77.19"
    },
    {
      "symbol": "ELSH",
      "issue": "recommendation price differs from market",
      "recommendationPrice": 11.61,
      "sourcePrice": 14.05,
      "diffPct": -17.37,
      "detail": "recommendations=11.61, market=14.05"
    },
    {
      "symbol": "MOIL",
      "issue": "recommendation price differs from market",
      "recommendationPrice": 0.48,
      "sourcePrice": 0.58,
      "diffPct": -17.24,
      "detail": "recommendations=0.48, market=0.58"
    },
    {
      "symbol": "NINH",
      "issue": "recommendation price differs from market",
      "recommendationPrice": 18.06,
      "sourcePrice": 21.73,
      "diffPct": -16.89,
      "detail": "recommendations=18.06, market=21.73"
    },
    {
      "symbol": "AMIA",
      "issue": "recommendation price differs from market",
      "recommendationPrice": 8.72,
      "sourcePrice": 10.46,
      "diffPct": -16.63,
      "detail": "recommendations=8.72, market=10.46"
    },
    {
      "symbol": "LCSW",
      "issue": "recommendation price differs from market",
      "recommendationPrice": 28.25,
      "sourcePrice": 33.55,
      "diffPct": -15.8,
      "detail": "recommendations=28.25, market=33.55"
    },
    {
      "symbol": "MAAL",
      "issue": "recommendation price differs from market",
      "recommendationPrice": 7.25,
      "sourcePrice": 8.6,
      "diffPct": -15.7,
      "detail": "recommendations=7.25, market=8.6"
    },
    {
      "symbol": "OFH",
      "issue": "recommendation price differs from market",
      "recommendationPrice": 0.6,
      "sourcePrice": 0.71,
      "diffPct": -15.49,
      "detail": "recommendations=0.6, market=0.71"
    },
    {
      "symbol": "SMFR",
      "issue": "recommendation price differs from market",
      "recommendationPrice": 194.67,
      "sourcePrice": 229.23,
      "diffPct": -15.08,
      "detail": "recommendations=194.67, market=229.23"
    },
    {
      "symbol": "KRDI",
      "issue": "recommendation price differs from market",
      "recommendationPrice": 0.34,
      "sourcePrice": 0.4,
      "diffPct": -15,
      "detail": "recommendations=0.34, market=0.4"
    },
    {
      "symbol": "GTWL",
      "issue": "recommendation price differs from market",
      "recommendationPrice": 89.74,
      "sourcePrice": 105.43,
      "diffPct": -14.88,
      "detail": "recommendations=89.74, market=105.43"
    },
    {
      "symbol": "MCRO",
      "issue": "recommendation price differs from market",
      "recommendationPrice": 1.2,
      "sourcePrice": 1.4,
      "diffPct": -14.29,
      "detail": "recommendations=1.2, market=1.4"
    },
    {
      "symbol": "CPCI",
      "issue": "recommendation price differs from market",
      "recommendationPrice": 404.91,
      "sourcePrice": 471.11,
      "diffPct": -14.05,
      "detail": "recommendations=404.91, market=471.11"
    },
    {
      "symbol": "ADPC",
      "issue": "recommendation price differs from market",
      "recommendationPrice": 3.45,
      "sourcePrice": 4.01,
      "diffPct": -13.97,
      "detail": "recommendations=3.45, market=4.01"
    },
    {
      "symbol": "EHDR",
      "issue": "recommendation price differs from market",
      "recommendationPrice": 2.5,
      "sourcePrice": 2.9,
      "diffPct": -13.79,
      "detail": "recommendations=2.5, market=2.9"
    },
    {
      "symbol": "ODIN",
      "issue": "recommendation price differs from market",
      "recommendationPrice": 2.18,
      "sourcePrice": 2.52,
      "diffPct": -13.49,
      "detail": "recommendations=2.18, market=2.52"
    },
    {
      "symbol": "PHTV",
      "issue": "recommendation price differs from market",
      "recommendationPrice": 272.72,
      "sourcePrice": 315,
      "diffPct": -13.42,
      "detail": "recommendations=272.72, market=315"
    },
    {
      "symbol": "ENGC",
      "issue": "recommendation price differs from market",
      "recommendationPrice": 36.6,
      "sourcePrice": 42.25,
      "diffPct": -13.37,
      "detail": "recommendations=36.6, market=42.25"
    },
    {
      "symbol": "AALR",
      "issue": "recommendation price differs from market",
      "recommendationPrice": 206.24,
      "sourcePrice": 237.54,
      "diffPct": -13.18,
      "detail": "recommendations=206.24, market=237.54"
    },
    {
      "symbol": "MPRC",
      "issue": "recommendation price differs from market",
      "recommendationPrice": 38.62,
      "sourcePrice": 44.43,
      "diffPct": -13.08,
      "detail": "recommendations=38.62, market=44.43"
    },
    {
      "symbol": "DSCW",
      "issue": "recommendation price differs from market",
      "recommendationPrice": 1.73,
      "sourcePrice": 1.99,
      "diffPct": -13.07,
      "detail": "recommendations=1.73, market=1.99"
    },
    {
      "symbol": "GDWA",
      "issue": "recommendation price differs from market",
      "recommendationPrice": 0.76,
      "sourcePrice": 0.87,
      "diffPct": -12.64,
      "detail": "recommendations=0.76, market=0.87"
    },
    {
      "symbol": "MIPH",
      "issue": "recommendation price differs from market",
      "recommendationPrice": 658.44,
      "sourcePrice": 753.6,
      "diffPct": -12.63,
      "detail": "recommendations=658.44, market=753.6"
    },
    {
      "symbol": "ARAB",
      "issue": "recommendation price differs from market",
      "recommendationPrice": 0.21,
      "sourcePrice": 0.24,
      "diffPct": -12.5,
      "detail": "recommendations=0.21, market=0.24"
    },
    {
      "symbol": "ZMID",
      "issue": "recommendation price differs from market",
      "recommendationPrice": 6.49,
      "sourcePrice": 7.41,
      "diffPct": -12.42,
      "detail": "recommendations=6.49, market=7.41"
    },
    {
      "symbol": "DTPP",
      "issue": "recommendation price differs from market",
      "recommendationPrice": 199.26,
      "sourcePrice": 226.58,
      "diffPct": -12.06,
      "detail": "recommendations=199.26, market=226.58"
    },
    {
      "symbol": "SIPC",
      "issue": "recommendation price differs from market",
      "recommendationPrice": 3.38,
      "sourcePrice": 3.84,
      "diffPct": -11.98,
      "detail": "recommendations=3.38, market=3.84"
    },
    {
      "symbol": "INFI",
      "issue": "recommendation price differs from market",
      "recommendationPrice": 93.41,
      "sourcePrice": 106.04,
      "diffPct": -11.91,
      "detail": "recommendations=93.41, market=106.04"
    },
    {
      "symbol": "SCFM",
      "issue": "recommendation price differs from market",
      "recommendationPrice": 238.16,
      "sourcePrice": 270.34,
      "diffPct": -11.9,
      "detail": "recommendations=238.16, market=270.34"
    },
    {
      "symbol": "EBSC",
      "issue": "recommendation price differs from market",
      "recommendationPrice": 2.1,
      "sourcePrice": 1.88,
      "diffPct": 11.7,
      "detail": "recommendations=2.1, market=1.88"
    },
    {
      "symbol": "UEFM",
      "issue": "recommendation price differs from market",
      "recommendationPrice": 477.14,
      "sourcePrice": 540.25,
      "diffPct": -11.68,
      "detail": "recommendations=477.14, market=540.25"
    },
    {
      "symbol": "MASR",
      "issue": "recommendation price differs from market",
      "recommendationPrice": 7.4,
      "sourcePrice": 8.36,
      "diffPct": -11.48,
      "detail": "recommendations=7.4, market=8.36"
    },
    {
      "symbol": "CCRS",
      "issue": "recommendation price differs from market",
      "recommendationPrice": 2.32,
      "sourcePrice": 2.61,
      "diffPct": -11.11,
      "detail": "recommendations=2.32, market=2.61"
    },
    {
      "symbol": "ASPI",
      "issue": "recommendation price differs from market",
      "recommendationPrice": 0.32,
      "sourcePrice": 0.36,
      "diffPct": -11.11,
      "detail": "recommendations=0.32, market=0.36"
    },
    {
      "symbol": "TANM",
      "issue": "recommendation price differs from market",
      "recommendationPrice": 5.25,
      "sourcePrice": 5.89,
      "diffPct": -10.87,
      "detail": "recommendations=5.25, market=5.89"
    },
    {
      "symbol": "MCQE",
      "issue": "recommendation price differs from market",
      "recommendationPrice": 172.1,
      "sourcePrice": 192.22,
      "diffPct": -10.47,
      "detail": "recommendations=172.1, market=192.22"
    },
    {
      "symbol": "WKOL",
      "issue": "recommendation price differs from market",
      "recommendationPrice": 281.12,
      "sourcePrice": 313.68,
      "diffPct": -10.38,
      "detail": "recommendations=281.12, market=313.68"
    },
    {
      "symbol": "WCDF",
      "issue": "recommendation price differs from market",
      "recommendationPrice": 506.06,
      "sourcePrice": 564.53,
      "diffPct": -10.36,
      "detail": "recommendations=506.06, market=564.53"
    },
    {
      "symbol": "GSSC",
      "issue": "recommendation price differs from market",
      "recommendationPrice": 244.44,
      "sourcePrice": 272,
      "diffPct": -10.13,
      "detail": "recommendations=244.44, market=272"
    },
    {
      "symbol": "COSG",
      "issue": "recommendation price differs from market",
      "recommendationPrice": 1.52,
      "sourcePrice": 1.69,
      "diffPct": -10.06,
      "detail": "recommendations=1.52, market=1.69"
    },
    {
      "symbol": "RUBX",
      "issue": "recommendation price differs from market",
      "recommendationPrice": 12.35,
      "sourcePrice": 13.71,
      "diffPct": -9.92,
      "detail": "recommendations=12.35, market=13.71"
    },
    {
      "symbol": "ALUM",
      "issue": "recommendation price differs from market",
      "recommendationPrice": 21.45,
      "sourcePrice": 23.8,
      "diffPct": -9.87,
      "detail": "recommendations=21.45, market=23.8"
    },
    {
      "symbol": "ETEL",
      "issue": "recommendation price differs from market",
      "recommendationPrice": 93.98,
      "sourcePrice": 104.15,
      "diffPct": -9.76,
      "detail": "recommendations=93.98, market=104.15"
    },
    {
      "symbol": "GMCI",
      "issue": "recommendation price differs from market",
      "recommendationPrice": 1.86,
      "sourcePrice": 2.06,
      "diffPct": -9.71,
      "detail": "recommendations=1.86, market=2.06"
    },
    {
      "symbol": "EFIH",
      "issue": "recommendation price differs from market",
      "recommendationPrice": 20.93,
      "sourcePrice": 23.16,
      "diffPct": -9.63,
      "detail": "recommendations=20.93, market=23.16"
    },
    {
      "symbol": "CIRA",
      "issue": "recommendation price differs from market",
      "recommendationPrice": 28.8,
      "sourcePrice": 31.81,
      "diffPct": -9.46,
      "detail": "recommendations=28.8, market=31.81"
    },
    {
      "symbol": "AIDC",
      "issue": "recommendation price differs from market",
      "recommendationPrice": 0.67,
      "sourcePrice": 0.74,
      "diffPct": -9.46,
      "detail": "recommendations=0.67, market=0.74"
    },
    {
      "symbol": "DAPH",
      "issue": "recommendation price differs from market",
      "recommendationPrice": 82.29,
      "sourcePrice": 90.85,
      "diffPct": -9.42,
      "detail": "recommendations=82.29, market=90.85"
    },
    {
      "symbol": "EEII",
      "issue": "recommendation price differs from market",
      "recommendationPrice": 2.5,
      "sourcePrice": 2.76,
      "diffPct": -9.42,
      "detail": "recommendations=2.5, market=2.76"
    },
    {
      "symbol": "IDRE",
      "issue": "recommendation price differs from market",
      "recommendationPrice": 43.65,
      "sourcePrice": 48.08,
      "diffPct": -9.21,
      "detail": "recommendations=43.65, market=48.08"
    },
    {
      "symbol": "CERA",
      "issue": "recommendation price differs from market",
      "recommendationPrice": 1.22,
      "sourcePrice": 1.34,
      "diffPct": -8.96,
      "detail": "recommendations=1.22, market=1.34"
    },
    {
      "symbol": "MPCI",
      "issue": "recommendation price differs from market",
      "recommendationPrice": 246,
      "sourcePrice": 269.84,
      "diffPct": -8.83,
      "detail": "recommendations=246, market=269.84"
    },
    {
      "symbol": "COMI",
      "issue": "recommendation price differs from market",
      "recommendationPrice": 127.4,
      "sourcePrice": 139.65,
      "diffPct": -8.77,
      "detail": "recommendations=127.4, market=139.65"
    },
    {
      "symbol": "ACGC",
      "issue": "recommendation price differs from market",
      "recommendationPrice": 9.23,
      "sourcePrice": 10.1,
      "diffPct": -8.61,
      "detail": "recommendations=9.23, market=10.1"
    },
    {
      "symbol": "AFDI",
      "issue": "recommendation price differs from market",
      "recommendationPrice": 44.34,
      "sourcePrice": 48.49,
      "diffPct": -8.56,
      "detail": "recommendations=44.34, market=48.49"
    },
    {
      "symbol": "RTVC",
      "issue": "recommendation price differs from market",
      "recommendationPrice": 3.79,
      "sourcePrice": 4.14,
      "diffPct": -8.45,
      "detail": "recommendations=3.79, market=4.14"
    },
    {
      "symbol": "RREI",
      "issue": "recommendation price differs from market",
      "recommendationPrice": 3.47,
      "sourcePrice": 3.78,
      "diffPct": -8.2,
      "detail": "recommendations=3.47, market=3.78"
    },
    {
      "symbol": "ACAMD",
      "issue": "recommendation price differs from market",
      "recommendationPrice": 2.25,
      "sourcePrice": 2.45,
      "diffPct": -8.16,
      "detail": "recommendations=2.25, market=2.45"
    },
    {
      "symbol": "APSW",
      "issue": "recommendation price differs from market",
      "recommendationPrice": 8.48,
      "sourcePrice": 9.23,
      "diffPct": -8.13,
      "detail": "recommendations=8.48, market=9.23"
    },
    {
      "symbol": "QNBE",
      "issue": "recommendation price differs from market",
      "recommendationPrice": 52.58,
      "sourcePrice": 57.18,
      "diffPct": -8.04,
      "detail": "recommendations=52.58, market=57.18"
    },
    {
      "symbol": "EXPA",
      "issue": "recommendation price differs from market",
      "recommendationPrice": 18.33,
      "sourcePrice": 19.93,
      "diffPct": -8.03,
      "detail": "recommendations=18.33, market=19.93"
    },
    {
      "symbol": "PRCL",
      "issue": "recommendation price differs from market",
      "recommendationPrice": 33,
      "sourcePrice": 35.87,
      "diffPct": -8,
      "detail": "recommendations=33, market=35.87"
    },
    {
      "symbol": "NCCW",
      "issue": "recommendation price differs from market",
      "recommendationPrice": 6.16,
      "sourcePrice": 6.69,
      "diffPct": -7.92,
      "detail": "recommendations=6.16, market=6.69"
    },
    {
      "symbol": "CCAP",
      "issue": "recommendation price differs from market",
      "recommendationPrice": 5.04,
      "sourcePrice": 5.45,
      "diffPct": -7.52,
      "detail": "recommendations=5.04, market=5.45"
    },
    {
      "symbol": "OCDI",
      "issue": "recommendation price differs from market",
      "recommendationPrice": 25.36,
      "sourcePrice": 27.4,
      "diffPct": -7.45,
      "detail": "recommendations=25.36, market=27.4"
    },
    {
      "symbol": "EASB",
      "issue": "recommendation price differs from market",
      "recommendationPrice": 7.54,
      "sourcePrice": 8.14,
      "diffPct": -7.37,
      "detail": "recommendations=7.54, market=8.14"
    },
    {
      "symbol": "EALR",
      "issue": "recommendation price differs from market",
      "recommendationPrice": 339.92,
      "sourcePrice": 365.95,
      "diffPct": -7.11,
      "detail": "recommendations=339.92, market=365.95"
    },
    {
      "symbol": "FERC",
      "issue": "recommendation price differs from market",
      "recommendationPrice": 73.55,
      "sourcePrice": 79.12,
      "diffPct": -7.04,
      "detail": "recommendations=73.55, market=79.12"
    },
    {
      "symbol": "AREH",
      "issue": "recommendation price differs from market",
      "recommendationPrice": 1.56,
      "sourcePrice": 1.46,
      "diffPct": 6.85,
      "detail": "recommendations=1.56, market=1.46"
    },
    {
      "symbol": "MOSC",
      "issue": "recommendation price differs from market",
      "recommendationPrice": 267.72,
      "sourcePrice": 287.32,
      "diffPct": -6.82,
      "detail": "recommendations=267.72, market=287.32"
    },
    {
      "symbol": "NAPR",
      "issue": "recommendation price differs from market",
      "recommendationPrice": 26.32,
      "sourcePrice": 28.23,
      "diffPct": -6.77,
      "detail": "recommendations=26.32, market=28.23"
    },
    {
      "symbol": "ABUK",
      "issue": "recommendation price differs from market",
      "recommendationPrice": 67.94,
      "sourcePrice": 72.64,
      "diffPct": -6.47,
      "detail": "recommendations=67.94, market=72.64"
    },
    {
      "symbol": "MFSC",
      "issue": "recommendation price differs from market",
      "recommendationPrice": 49.48,
      "sourcePrice": 46.48,
      "diffPct": 6.45,
      "detail": "recommendations=49.48, market=46.48"
    },
    {
      "symbol": "AJWA",
      "issue": "recommendation price differs from market",
      "recommendationPrice": 179.07,
      "sourcePrice": 168.29,
      "diffPct": 6.41,
      "detail": "recommendations=179.07, market=168.29"
    },
    {
      "symbol": "TMGH",
      "issue": "recommendation price differs from market",
      "recommendationPrice": 94.97,
      "sourcePrice": 101.41,
      "diffPct": -6.35,
      "detail": "recommendations=94.97, market=101.41"
    },
    {
      "symbol": "ELEC",
      "issue": "recommendation price differs from market",
      "recommendationPrice": 2.1,
      "sourcePrice": 2.24,
      "diffPct": -6.25,
      "detail": "recommendations=2.1, market=2.24"
    },
    {
      "symbol": "EGBE",
      "issue": "recommendation price differs from market",
      "recommendationPrice": 0.45,
      "sourcePrice": 0.48,
      "diffPct": -6.25,
      "detail": "recommendations=0.45, market=0.48"
    },
    {
      "symbol": "SNFC",
      "issue": "recommendation price differs from market",
      "recommendationPrice": 12.08,
      "sourcePrice": 11.38,
      "diffPct": 6.15,
      "detail": "recommendations=12.08, market=11.38"
    },
    {
      "symbol": "EGCH",
      "issue": "recommendation price differs from market",
      "recommendationPrice": 12.25,
      "sourcePrice": 13.04,
      "diffPct": -6.06,
      "detail": "recommendations=12.25, market=13.04"
    },
    {
      "symbol": "OIH",
      "issue": "recommendation price differs from market",
      "recommendationPrice": 1.41,
      "sourcePrice": 1.5,
      "diffPct": -6,
      "detail": "recommendations=1.41, market=1.5"
    },
    {
      "symbol": "VLMRA",
      "issue": "recommendation price differs from market",
      "recommendationPrice": 28.2,
      "sourcePrice": 29.99,
      "diffPct": -5.97,
      "detail": "recommendations=28.2, market=29.99"
    },
    {
      "symbol": "PRMH",
      "issue": "recommendation price differs from market",
      "recommendationPrice": 2.57,
      "sourcePrice": 2.73,
      "diffPct": -5.86,
      "detail": "recommendations=2.57, market=2.73"
    },
    {
      "symbol": "ZEOT",
      "issue": "recommendation price differs from market",
      "recommendationPrice": 11.04,
      "sourcePrice": 11.71,
      "diffPct": -5.72,
      "detail": "recommendations=11.04, market=11.71"
    },
    {
      "symbol": "MOED",
      "issue": "recommendation price differs from market",
      "recommendationPrice": 0.68,
      "sourcePrice": 0.72,
      "diffPct": -5.56,
      "detail": "recommendations=0.68, market=0.72"
    },
    {
      "symbol": "AMOC",
      "issue": "recommendation price differs from market",
      "recommendationPrice": 7.76,
      "sourcePrice": 8.21,
      "diffPct": -5.48,
      "detail": "recommendations=7.76, market=8.21"
    },
    {
      "symbol": "ADIB",
      "issue": "recommendation price differs from market",
      "recommendationPrice": 46.64,
      "sourcePrice": 49.3,
      "diffPct": -5.4,
      "detail": "recommendations=46.64, market=49.3"
    },
    {
      "symbol": "SWDY",
      "issue": "recommendation price differs from market",
      "recommendationPrice": 87,
      "sourcePrice": 91.9,
      "diffPct": -5.33,
      "detail": "recommendations=87, market=91.9"
    },
    {
      "symbol": "ADCI",
      "issue": "recommendation price differs from market",
      "recommendationPrice": 240.97,
      "sourcePrice": 254.53,
      "diffPct": -5.33,
      "detail": "recommendations=240.97, market=254.53"
    },
    {
      "symbol": "COPR",
      "issue": "recommendation price differs from market",
      "recommendationPrice": 0.36,
      "sourcePrice": 0.38,
      "diffPct": -5.26,
      "detail": "recommendations=0.36, market=0.38"
    },
    {
      "symbol": "SPIN",
      "issue": "recommendation price differs from market",
      "recommendationPrice": 14.17,
      "sourcePrice": 14.95,
      "diffPct": -5.22,
      "detail": "recommendations=14.17, market=14.95"
    },
    {
      "symbol": "EGAS",
      "issue": "recommendation price differs from market",
      "recommendationPrice": 49.63,
      "sourcePrice": 52.35,
      "diffPct": -5.2,
      "detail": "recommendations=49.63, market=52.35"
    },
    {
      "symbol": "FWRY",
      "issue": "recommendation price differs from market",
      "recommendationPrice": 18.37,
      "sourcePrice": 19.35,
      "diffPct": -5.06,
      "detail": "recommendations=18.37, market=19.35"
    },
    {
      "symbol": "EGAL",
      "issue": "recommendation price differs from market",
      "recommendationPrice": 285.88,
      "sourcePrice": 301.04,
      "diffPct": -5.04,
      "detail": "recommendations=285.88, market=301.04"
    },
    {
      "symbol": "SDTI",
      "issue": "recommendation price differs from market",
      "recommendationPrice": 46.44,
      "sourcePrice": 48.86,
      "diffPct": -4.95,
      "detail": "recommendations=46.44, market=48.86"
    },
    {
      "symbol": "MFPC",
      "issue": "recommendation price differs from market",
      "recommendationPrice": 35.72,
      "sourcePrice": 37.55,
      "diffPct": -4.87,
      "detail": "recommendations=35.72, market=37.55"
    },
    {
      "symbol": "MICH",
      "issue": "recommendation price differs from market",
      "recommendationPrice": 37.54,
      "sourcePrice": 39.44,
      "diffPct": -4.82,
      "detail": "recommendations=37.54, market=39.44"
    },
    {
      "symbol": "ALCN",
      "issue": "recommendation price differs from market",
      "recommendationPrice": 28.34,
      "sourcePrice": 29.7,
      "diffPct": -4.58,
      "detail": "recommendations=28.34, market=29.7"
    },
    {
      "symbol": "SPMD",
      "issue": "recommendation price differs from market",
      "recommendationPrice": 0.43,
      "sourcePrice": 0.45,
      "diffPct": -4.44,
      "detail": "recommendations=0.43, market=0.45"
    },
    {
      "symbol": "ACAP",
      "issue": "recommendation price differs from market",
      "recommendationPrice": 8.56,
      "sourcePrice": 8.95,
      "diffPct": -4.36,
      "detail": "recommendations=8.56, market=8.95"
    },
    {
      "symbol": "AIHC",
      "issue": "recommendation price differs from market",
      "recommendationPrice": 0.47,
      "sourcePrice": 0.49,
      "diffPct": -4.08,
      "detail": "recommendations=0.47, market=0.49"
    },
    {
      "symbol": "SAUD",
      "issue": "recommendation price differs from market",
      "recommendationPrice": 21.09,
      "sourcePrice": 21.95,
      "diffPct": -3.92,
      "detail": "recommendations=21.09, market=21.95"
    },
    {
      "symbol": "PHDC",
      "issue": "recommendation price differs from market",
      "recommendationPrice": 14.58,
      "sourcePrice": 15.17,
      "diffPct": -3.89,
      "detail": "recommendations=14.58, market=15.17"
    },
    {
      "symbol": "BTFH",
      "issue": "recommendation price differs from market",
      "recommendationPrice": 2.97,
      "sourcePrice": 3.09,
      "diffPct": -3.88,
      "detail": "recommendations=2.97, market=3.09"
    },
    {
      "symbol": "NEDA",
      "issue": "recommendation price differs from market",
      "recommendationPrice": 2.75,
      "sourcePrice": 2.86,
      "diffPct": -3.85,
      "detail": "recommendations=2.75, market=2.86"
    },
    {
      "symbol": "JUFO",
      "issue": "recommendation price differs from market",
      "recommendationPrice": 29.99,
      "sourcePrice": 28.9,
      "diffPct": 3.77,
      "detail": "recommendations=29.99, market=28.9"
    },
    {
      "symbol": "VALU",
      "issue": "recommendation price differs from market",
      "recommendationPrice": 12.05,
      "sourcePrice": 12.5,
      "diffPct": -3.6,
      "detail": "recommendations=12.05, market=12.5"
    },
    {
      "symbol": "CANA",
      "issue": "recommendation price differs from market",
      "recommendationPrice": 35.74,
      "sourcePrice": 37,
      "diffPct": -3.41,
      "detail": "recommendations=35.74, market=37"
    },
    {
      "symbol": "KORA",
      "issue": "recommendation price differs from market",
      "recommendationPrice": 3.45,
      "sourcePrice": 3.34,
      "diffPct": 3.29,
      "detail": "recommendations=3.45, market=3.34"
    },
    {
      "symbol": "BINV",
      "issue": "recommendation price differs from market",
      "recommendationPrice": 46.04,
      "sourcePrice": 47.57,
      "diffPct": -3.22,
      "detail": "recommendations=46.04, market=47.57"
    },
    {
      "symbol": "ASCM",
      "issue": "recommendation price differs from market",
      "recommendationPrice": 59.26,
      "sourcePrice": 61.08,
      "diffPct": -2.98,
      "detail": "recommendations=59.26, market=61.08"
    },
    {
      "symbol": "ARCC",
      "issue": "recommendation price differs from market",
      "recommendationPrice": 55.44,
      "sourcePrice": 57.11,
      "diffPct": -2.92,
      "detail": "recommendations=55.44, market=57.11"
    },
    {
      "symbol": "ECAP",
      "issue": "recommendation price differs from market",
      "recommendationPrice": 32.72,
      "sourcePrice": 33.7,
      "diffPct": -2.91,
      "detail": "recommendations=32.72, market=33.7"
    },
    {
      "symbol": "IRON",
      "issue": "recommendation price differs from market",
      "recommendationPrice": 32.21,
      "sourcePrice": 31.31,
      "diffPct": 2.87,
      "detail": "recommendations=32.21, market=31.31"
    },
    {
      "symbol": "PHAR",
      "issue": "recommendation price differs from market",
      "recommendationPrice": 88.21,
      "sourcePrice": 90.75,
      "diffPct": -2.8,
      "detail": "recommendations=88.21, market=90.75"
    },
    {
      "symbol": "CSAG",
      "issue": "recommendation price differs from market",
      "recommendationPrice": 32.58,
      "sourcePrice": 33.51,
      "diffPct": -2.78,
      "detail": "recommendations=32.58, market=33.51"
    },
    {
      "symbol": "MENA",
      "issue": "recommendation price differs from market",
      "recommendationPrice": 6.89,
      "sourcePrice": 7.08,
      "diffPct": -2.68,
      "detail": "recommendations=6.89, market=7.08"
    },
    {
      "symbol": "SVCE",
      "issue": "recommendation price differs from market",
      "recommendationPrice": 9.63,
      "sourcePrice": 9.38,
      "diffPct": 2.67,
      "detail": "recommendations=9.63, market=9.38"
    },
    {
      "symbol": "ORHD",
      "issue": "recommendation price differs from market",
      "recommendationPrice": 38.25,
      "sourcePrice": 39.3,
      "diffPct": -2.67,
      "detail": "recommendations=38.25, market=39.3"
    },
    {
      "symbol": "ORWE",
      "issue": "recommendation price differs from market",
      "recommendationPrice": 22.39,
      "sourcePrice": 23,
      "diffPct": -2.65,
      "detail": "recommendations=22.39, market=23"
    },
    {
      "symbol": "SCTS",
      "issue": "recommendation price differs from market",
      "recommendationPrice": 626.62,
      "sourcePrice": 611.44,
      "diffPct": 2.48,
      "detail": "recommendations=626.62, market=611.44"
    },
    {
      "symbol": "ETRS",
      "issue": "recommendation price differs from market",
      "recommendationPrice": 10.6,
      "sourcePrice": 10.85,
      "diffPct": -2.3,
      "detail": "recommendations=10.6, market=10.85"
    },
    {
      "symbol": "EFID",
      "issue": "recommendation price differs from market",
      "recommendationPrice": 27.37,
      "sourcePrice": 27.99,
      "diffPct": -2.22,
      "detail": "recommendations=27.37, market=27.99"
    },
    {
      "symbol": "CIEB",
      "issue": "recommendation price differs from market",
      "recommendationPrice": 23.92,
      "sourcePrice": 24.45,
      "diffPct": -2.17,
      "detail": "recommendations=23.92, market=24.45"
    },
    {
      "symbol": "POUL",
      "issue": "recommendation price differs from market",
      "recommendationPrice": 38,
      "sourcePrice": 38.82,
      "diffPct": -2.11,
      "detail": "recommendations=38, market=38.82"
    },
    {
      "symbol": "DOMT",
      "issue": "recommendation price differs from market",
      "recommendationPrice": 27.23,
      "sourcePrice": 26.68,
      "diffPct": 2.06,
      "detail": "recommendations=27.23, market=26.68"
    },
    {
      "symbol": "EMFD",
      "issue": "recommendation price differs from market",
      "recommendationPrice": 11.56,
      "sourcePrice": 11.8,
      "diffPct": -2.03,
      "detail": "recommendations=11.56, market=11.8"
    },
    {
      "symbol": "OLFI",
      "issue": "recommendation price differs from market",
      "recommendationPrice": 22.29,
      "sourcePrice": 22.75,
      "diffPct": -2.02,
      "detail": "recommendations=22.29, market=22.75"
    },
    {
      "symbol": "DGTZ",
      "issue": "recommendation price differs from market",
      "recommendationPrice": 2.51,
      "sourcePrice": 2.56,
      "diffPct": -1.95,
      "detail": "recommendations=2.51, market=2.56"
    },
    {
      "symbol": "ROTO",
      "issue": "recommendation price differs from market",
      "recommendationPrice": 41.48,
      "sourcePrice": 42.29,
      "diffPct": -1.92,
      "detail": "recommendations=41.48, market=42.29"
    },
    {
      "symbol": "ATQA",
      "issue": "recommendation price differs from market",
      "recommendationPrice": 9.47,
      "sourcePrice": 9.65,
      "diffPct": -1.87,
      "detail": "recommendations=9.47, market=9.65"
    },
    {
      "symbol": "CNFN",
      "issue": "recommendation price differs from market",
      "recommendationPrice": 4.76,
      "sourcePrice": 4.85,
      "diffPct": -1.86,
      "detail": "recommendations=4.76, market=4.85"
    },
    {
      "symbol": "UBEE",
      "issue": "recommendation price differs from market",
      "recommendationPrice": 13.47,
      "sourcePrice": 13.72,
      "diffPct": -1.82,
      "detail": "recommendations=13.47, market=13.72"
    },
    {
      "symbol": "FAIT",
      "issue": "recommendation price differs from market",
      "recommendationPrice": 36.98,
      "sourcePrice": 37.65,
      "diffPct": -1.78,
      "detail": "recommendations=36.98, market=37.65"
    },
    {
      "symbol": "AXPH",
      "issue": "recommendation price differs from market",
      "recommendationPrice": 1212.35,
      "sourcePrice": 1233.15,
      "diffPct": -1.69,
      "detail": "recommendations=1212.35, market=1233.15"
    },
    {
      "symbol": "VLMR",
      "issue": "recommendation price differs from market",
      "recommendationPrice": 0.67,
      "sourcePrice": 0.66,
      "diffPct": 1.52,
      "detail": "recommendations=0.67, market=0.66"
    },
    {
      "symbol": "ICID",
      "issue": "recommendation price differs from market",
      "recommendationPrice": 7.98,
      "sourcePrice": 8.1,
      "diffPct": -1.48,
      "detail": "recommendations=7.98, market=8.1"
    },
    {
      "symbol": "CLHO",
      "issue": "recommendation price differs from market",
      "recommendationPrice": 16.5,
      "sourcePrice": 16.74,
      "diffPct": -1.43,
      "detail": "recommendations=16.5, market=16.74"
    },
    {
      "symbol": "MBSC",
      "issue": "recommendation price differs from market",
      "recommendationPrice": 242.18,
      "sourcePrice": 245.67,
      "diffPct": -1.42,
      "detail": "recommendations=242.18, market=245.67"
    },
    {
      "symbol": "BONY",
      "issue": "recommendation price differs from market",
      "recommendationPrice": 4.88,
      "sourcePrice": 4.95,
      "diffPct": -1.41,
      "detail": "recommendations=4.88, market=4.95"
    },
    {
      "symbol": "RACC",
      "issue": "recommendation price differs from market",
      "recommendationPrice": 9.85,
      "sourcePrice": 9.98,
      "diffPct": -1.3,
      "detail": "recommendations=9.85, market=9.98"
    },
    {
      "symbol": "KZPC",
      "issue": "recommendation price differs from market",
      "recommendationPrice": 8.47,
      "sourcePrice": 8.58,
      "diffPct": -1.28,
      "detail": "recommendations=8.47, market=8.58"
    },
    {
      "symbol": "ORAS",
      "issue": "recommendation price differs from market",
      "recommendationPrice": 720.42,
      "sourcePrice": 711.55,
      "diffPct": 1.25,
      "detail": "recommendations=720.42, market=711.55"
    },
    {
      "symbol": "ISMQ",
      "issue": "recommendation price differs from market",
      "recommendationPrice": 9.34,
      "sourcePrice": 9.23,
      "diffPct": 1.19,
      "detail": "recommendations=9.34, market=9.23"
    },
    {
      "symbol": "CICH",
      "issue": "recommendation price differs from market",
      "recommendationPrice": 11.87,
      "sourcePrice": 12.01,
      "diffPct": -1.17,
      "detail": "recommendations=11.87, market=12.01"
    },
    {
      "symbol": "MPCO",
      "issue": "recommendation price differs from market",
      "recommendationPrice": 1.84,
      "sourcePrice": 1.86,
      "diffPct": -1.08,
      "detail": "recommendations=1.84, market=1.86"
    },
    {
      "symbol": "MTIE",
      "issue": "recommendation price differs from market",
      "recommendationPrice": 9.34,
      "sourcePrice": 9.44,
      "diffPct": -1.06,
      "detail": "recommendations=9.34, market=9.44"
    },
    {
      "symbol": "ELWA",
      "issue": "recommendation price differs from market",
      "recommendationPrice": 1.95,
      "sourcePrice": 1.93,
      "diffPct": 1.04,
      "detail": "recommendations=1.95, market=1.93"
    },
    {
      "symbol": "OBRI",
      "issue": "recommendation price differs from market",
      "recommendationPrice": 34.94,
      "sourcePrice": 35.3,
      "diffPct": -1.02,
      "detail": "recommendations=34.94, market=35.3"
    },
    {
      "symbol": "FAITA",
      "issue": "recommendation price differs from market",
      "recommendationPrice": 0.99,
      "sourcePrice": 0.98,
      "diffPct": 1.02,
      "detail": "recommendations=0.99, market=0.98"
    },
    {
      "symbol": "RAYA",
      "issue": "recommendation price differs from market",
      "recommendationPrice": 7.67,
      "sourcePrice": 7.6,
      "diffPct": 0.92,
      "detail": "recommendations=7.67, market=7.6"
    },
    {
      "symbol": "GPIM",
      "issue": "recommendation price differs from market",
      "recommendationPrice": 1.11,
      "sourcePrice": 1.12,
      "diffPct": -0.89,
      "detail": "recommendations=1.11, market=1.12"
    },
    {
      "symbol": "TALM",
      "issue": "recommendation price differs from market",
      "recommendationPrice": 15.8,
      "sourcePrice": 15.93,
      "diffPct": -0.82,
      "detail": "recommendations=15.8, market=15.93"
    }
  ],
  "discrepancies": [
    {
      "symbol": "MHOT",
      "issue": "recommendation price differs from market",
      "recommendationPrice": 33.98,
      "sourcePrice": 16.57,
      "diffPct": 105.07,
      "detail": "recommendations=33.98, market=16.57"
    },
    {
      "symbol": "HDBK",
      "issue": "recommendation price differs from market",
      "recommendationPrice": 166.67,
      "sourcePrice": 82.84,
      "diffPct": 101.2,
      "detail": "recommendations=166.67, market=82.84"
    },
    {
      "symbol": "AMES",
      "issue": "recommendation price differs from market",
      "recommendationPrice": 60.51,
      "sourcePrice": 107.94,
      "diffPct": -43.94,
      "detail": "recommendations=60.51, market=107.94"
    },
    {
      "symbol": "AMER",
      "issue": "recommendation price differs from market",
      "recommendationPrice": 2.42,
      "sourcePrice": 4.25,
      "diffPct": -43.06,
      "detail": "recommendations=2.42, market=4.25"
    },
    {
      "symbol": "GGCC",
      "issue": "recommendation price differs from market",
      "recommendationPrice": 0.49,
      "sourcePrice": 0.84,
      "diffPct": -41.67,
      "detail": "recommendations=0.49, market=0.84"
    },
    {
      "symbol": "UEGC",
      "issue": "recommendation price differs from market",
      "recommendationPrice": 1.45,
      "sourcePrice": 2.41,
      "diffPct": -39.83,
      "detail": "recommendations=1.45, market=2.41"
    },
    {
      "symbol": "CAED",
      "issue": "recommendation price differs from market",
      "recommendationPrice": 71.33,
      "sourcePrice": 116.02,
      "diffPct": -38.52,
      "detail": "recommendations=71.33, market=116.02"
    },
    {
      "symbol": "BIOC",
      "issue": "recommendation price differs from market",
      "recommendationPrice": 71.48,
      "sourcePrice": 109.85,
      "diffPct": -34.93,
      "detail": "recommendations=71.48, market=109.85"
    },
    {
      "symbol": "ELKA",
      "issue": "recommendation price differs from market",
      "recommendationPrice": 1.36,
      "sourcePrice": 2.06,
      "diffPct": -33.98,
      "detail": "recommendations=1.36, market=2.06"
    },
    {
      "symbol": "KWIN",
      "issue": "recommendation price differs from market",
      "recommendationPrice": 67.44,
      "sourcePrice": 99.02,
      "diffPct": -31.89,
      "detail": "recommendations=67.44, market=99.02"
    },
    {
      "symbol": "AFMC",
      "issue": "recommendation price differs from market",
      "recommendationPrice": 69.44,
      "sourcePrice": 100.74,
      "diffPct": -31.07,
      "detail": "recommendations=69.44, market=100.74"
    },
    {
      "symbol": "UNIT",
      "issue": "recommendation price differs from market",
      "recommendationPrice": 12.95,
      "sourcePrice": 18.5,
      "diffPct": -30,
      "detail": "recommendations=12.95, market=18.5"
    },
    {
      "symbol": "TYCN",
      "issue": "recommendation price differs from market",
      "recommendationPrice": 27.51,
      "sourcePrice": 21.23,
      "diffPct": 29.58,
      "detail": "recommendations=27.51, market=21.23"
    },
    {
      "symbol": "GIHD",
      "issue": "recommendation price differs from market",
      "recommendationPrice": 42.06,
      "sourcePrice": 57.25,
      "diffPct": -26.53,
      "detail": "recommendations=42.06, market=57.25"
    },
    {
      "symbol": "KABO",
      "issue": "recommendation price differs from market",
      "recommendationPrice": 6.33,
      "sourcePrice": 8.55,
      "diffPct": -25.96,
      "detail": "recommendations=6.33, market=8.55"
    },
    {
      "symbol": "GTEX",
      "issue": "recommendation price differs from market",
      "recommendationPrice": 0.03,
      "sourcePrice": 0.04,
      "diffPct": -25,
      "detail": "recommendations=0.03, market=0.04"
    },
    {
      "symbol": "NHPS",
      "issue": "recommendation price differs from market",
      "recommendationPrice": 68,
      "sourcePrice": 90.52,
      "diffPct": -24.88,
      "detail": "recommendations=68, market=90.52"
    },
    {
      "symbol": "CRST",
      "issue": "recommendation price differs from market",
      "recommendationPrice": 1.32,
      "sourcePrice": 1.73,
      "diffPct": -23.7,
      "detail": "recommendations=1.32, market=1.73"
    },
    {
      "symbol": "NARE",
      "issue": "recommendation price differs from market",
      "recommendationPrice": 13.9,
      "sourcePrice": 18.2,
      "diffPct": -23.63,
      "detail": "recommendations=13.9, market=18.2"
    },
    {
      "symbol": "HELI",
      "issue": "recommendation price differs from market",
      "recommendationPrice": 6.43,
      "sourcePrice": 8.35,
      "diffPct": -22.99,
      "detail": "recommendations=6.43, market=8.35"
    },
    {
      "symbol": "MILS",
      "issue": "recommendation price differs from market",
      "recommendationPrice": 129.64,
      "sourcePrice": 168.23,
      "diffPct": -22.94,
      "detail": "recommendations=129.64, market=168.23"
    },
    {
      "symbol": "OCPH",
      "issue": "recommendation price differs from market",
      "recommendationPrice": 356.52,
      "sourcePrice": 457.33,
      "diffPct": -22.04,
      "detail": "recommendations=356.52, market=457.33"
    },
    {
      "symbol": "UNIP",
      "issue": "recommendation price differs from market",
      "recommendationPrice": 0.33,
      "sourcePrice": 0.42,
      "diffPct": -21.43,
      "detail": "recommendations=0.33, market=0.42"
    },
    {
      "symbol": "MEPA",
      "issue": "recommendation price differs from market",
      "recommendationPrice": 1.57,
      "sourcePrice": 1.99,
      "diffPct": -21.11,
      "detail": "recommendations=1.57, market=1.99"
    },
    {
      "symbol": "SEIG",
      "issue": "recommendation price differs from market",
      "recommendationPrice": 190.54,
      "sourcePrice": 241.46,
      "diffPct": -21.09,
      "detail": "recommendations=190.54, market=241.46"
    },
    {
      "symbol": "NIPH",
      "issue": "recommendation price differs from market",
      "recommendationPrice": 180.06,
      "sourcePrice": 228.11,
      "diffPct": -21.06,
      "detail": "recommendations=180.06, market=228.11"
    },
    {
      "symbol": "PRDC",
      "issue": "recommendation price differs from market",
      "recommendationPrice": 7.7,
      "sourcePrice": 9.71,
      "diffPct": -20.7,
      "detail": "recommendations=7.7, market=9.71"
    },
    {
      "symbol": "CEFM",
      "issue": "recommendation price differs from market",
      "recommendationPrice": 100.07,
      "sourcePrice": 125.12,
      "diffPct": -20.02,
      "detail": "recommendations=100.07, market=125.12"
    },
    {
      "symbol": "EPCO",
      "issue": "recommendation price differs from market",
      "recommendationPrice": 8.7,
      "sourcePrice": 10.74,
      "diffPct": -18.99,
      "detail": "recommendations=8.7, market=10.74"
    },
    {
      "symbol": "GRCA",
      "issue": "recommendation price differs from market",
      "recommendationPrice": 52.29,
      "sourcePrice": 64.1,
      "diffPct": -18.42,
      "detail": "recommendations=52.29, market=64.1"
    },
    {
      "symbol": "SCEM",
      "issue": "recommendation price differs from market",
      "recommendationPrice": 63.32,
      "sourcePrice": 77.19,
      "diffPct": -17.97,
      "detail": "recommendations=63.32, market=77.19"
    },
    {
      "symbol": "ELSH",
      "issue": "recommendation price differs from market",
      "recommendationPrice": 11.61,
      "sourcePrice": 14.05,
      "diffPct": -17.37,
      "detail": "recommendations=11.61, market=14.05"
    },
    {
      "symbol": "MOIL",
      "issue": "recommendation price differs from market",
      "recommendationPrice": 0.48,
      "sourcePrice": 0.58,
      "diffPct": -17.24,
      "detail": "recommendations=0.48, market=0.58"
    },
    {
      "symbol": "NINH",
      "issue": "recommendation price differs from market",
      "recommendationPrice": 18.06,
      "sourcePrice": 21.73,
      "diffPct": -16.89,
      "detail": "recommendations=18.06, market=21.73"
    },
    {
      "symbol": "AMIA",
      "issue": "recommendation price differs from market",
      "recommendationPrice": 8.72,
      "sourcePrice": 10.46,
      "diffPct": -16.63,
      "detail": "recommendations=8.72, market=10.46"
    },
    {
      "symbol": "LCSW",
      "issue": "recommendation price differs from market",
      "recommendationPrice": 28.25,
      "sourcePrice": 33.55,
      "diffPct": -15.8,
      "detail": "recommendations=28.25, market=33.55"
    },
    {
      "symbol": "MAAL",
      "issue": "recommendation price differs from market",
      "recommendationPrice": 7.25,
      "sourcePrice": 8.6,
      "diffPct": -15.7,
      "detail": "recommendations=7.25, market=8.6"
    },
    {
      "symbol": "OFH",
      "issue": "recommendation price differs from market",
      "recommendationPrice": 0.6,
      "sourcePrice": 0.71,
      "diffPct": -15.49,
      "detail": "recommendations=0.6, market=0.71"
    },
    {
      "symbol": "SMFR",
      "issue": "recommendation price differs from market",
      "recommendationPrice": 194.67,
      "sourcePrice": 229.23,
      "diffPct": -15.08,
      "detail": "recommendations=194.67, market=229.23"
    },
    {
      "symbol": "KRDI",
      "issue": "recommendation price differs from market",
      "recommendationPrice": 0.34,
      "sourcePrice": 0.4,
      "diffPct": -15,
      "detail": "recommendations=0.34, market=0.4"
    },
    {
      "symbol": "GTWL",
      "issue": "recommendation price differs from market",
      "recommendationPrice": 89.74,
      "sourcePrice": 105.43,
      "diffPct": -14.88,
      "detail": "recommendations=89.74, market=105.43"
    },
    {
      "symbol": "MCRO",
      "issue": "recommendation price differs from market",
      "recommendationPrice": 1.2,
      "sourcePrice": 1.4,
      "diffPct": -14.29,
      "detail": "recommendations=1.2, market=1.4"
    },
    {
      "symbol": "CPCI",
      "issue": "recommendation price differs from market",
      "recommendationPrice": 404.91,
      "sourcePrice": 471.11,
      "diffPct": -14.05,
      "detail": "recommendations=404.91, market=471.11"
    },
    {
      "symbol": "ADPC",
      "issue": "recommendation price differs from market",
      "recommendationPrice": 3.45,
      "sourcePrice": 4.01,
      "diffPct": -13.97,
      "detail": "recommendations=3.45, market=4.01"
    },
    {
      "symbol": "EHDR",
      "issue": "recommendation price differs from market",
      "recommendationPrice": 2.5,
      "sourcePrice": 2.9,
      "diffPct": -13.79,
      "detail": "recommendations=2.5, market=2.9"
    },
    {
      "symbol": "ODIN",
      "issue": "recommendation price differs from market",
      "recommendationPrice": 2.18,
      "sourcePrice": 2.52,
      "diffPct": -13.49,
      "detail": "recommendations=2.18, market=2.52"
    },
    {
      "symbol": "PHTV",
      "issue": "recommendation price differs from market",
      "recommendationPrice": 272.72,
      "sourcePrice": 315,
      "diffPct": -13.42,
      "detail": "recommendations=272.72, market=315"
    },
    {
      "symbol": "ENGC",
      "issue": "recommendation price differs from market",
      "recommendationPrice": 36.6,
      "sourcePrice": 42.25,
      "diffPct": -13.37,
      "detail": "recommendations=36.6, market=42.25"
    },
    {
      "symbol": "AALR",
      "issue": "recommendation price differs from market",
      "recommendationPrice": 206.24,
      "sourcePrice": 237.54,
      "diffPct": -13.18,
      "detail": "recommendations=206.24, market=237.54"
    },
    {
      "symbol": "MPRC",
      "issue": "recommendation price differs from market",
      "recommendationPrice": 38.62,
      "sourcePrice": 44.43,
      "diffPct": -13.08,
      "detail": "recommendations=38.62, market=44.43"
    },
    {
      "symbol": "DSCW",
      "issue": "recommendation price differs from market",
      "recommendationPrice": 1.73,
      "sourcePrice": 1.99,
      "diffPct": -13.07,
      "detail": "recommendations=1.73, market=1.99"
    },
    {
      "symbol": "GDWA",
      "issue": "recommendation price differs from market",
      "recommendationPrice": 0.76,
      "sourcePrice": 0.87,
      "diffPct": -12.64,
      "detail": "recommendations=0.76, market=0.87"
    },
    {
      "symbol": "MIPH",
      "issue": "recommendation price differs from market",
      "recommendationPrice": 658.44,
      "sourcePrice": 753.6,
      "diffPct": -12.63,
      "detail": "recommendations=658.44, market=753.6"
    },
    {
      "symbol": "ARAB",
      "issue": "recommendation price differs from market",
      "recommendationPrice": 0.21,
      "sourcePrice": 0.24,
      "diffPct": -12.5,
      "detail": "recommendations=0.21, market=0.24"
    },
    {
      "symbol": "ZMID",
      "issue": "recommendation price differs from market",
      "recommendationPrice": 6.49,
      "sourcePrice": 7.41,
      "diffPct": -12.42,
      "detail": "recommendations=6.49, market=7.41"
    },
    {
      "symbol": "DTPP",
      "issue": "recommendation price differs from market",
      "recommendationPrice": 199.26,
      "sourcePrice": 226.58,
      "diffPct": -12.06,
      "detail": "recommendations=199.26, market=226.58"
    },
    {
      "symbol": "SIPC",
      "issue": "recommendation price differs from market",
      "recommendationPrice": 3.38,
      "sourcePrice": 3.84,
      "diffPct": -11.98,
      "detail": "recommendations=3.38, market=3.84"
    },
    {
      "symbol": "INFI",
      "issue": "recommendation price differs from market",
      "recommendationPrice": 93.41,
      "sourcePrice": 106.04,
      "diffPct": -11.91,
      "detail": "recommendations=93.41, market=106.04"
    },
    {
      "symbol": "SCFM",
      "issue": "recommendation price differs from market",
      "recommendationPrice": 238.16,
      "sourcePrice": 270.34,
      "diffPct": -11.9,
      "detail": "recommendations=238.16, market=270.34"
    },
    {
      "symbol": "EBSC",
      "issue": "recommendation price differs from market",
      "recommendationPrice": 2.1,
      "sourcePrice": 1.88,
      "diffPct": 11.7,
      "detail": "recommendations=2.1, market=1.88"
    },
    {
      "symbol": "UEFM",
      "issue": "recommendation price differs from market",
      "recommendationPrice": 477.14,
      "sourcePrice": 540.25,
      "diffPct": -11.68,
      "detail": "recommendations=477.14, market=540.25"
    },
    {
      "symbol": "MASR",
      "issue": "recommendation price differs from market",
      "recommendationPrice": 7.4,
      "sourcePrice": 8.36,
      "diffPct": -11.48,
      "detail": "recommendations=7.4, market=8.36"
    },
    {
      "symbol": "CCRS",
      "issue": "recommendation price differs from market",
      "recommendationPrice": 2.32,
      "sourcePrice": 2.61,
      "diffPct": -11.11,
      "detail": "recommendations=2.32, market=2.61"
    },
    {
      "symbol": "ASPI",
      "issue": "recommendation price differs from market",
      "recommendationPrice": 0.32,
      "sourcePrice": 0.36,
      "diffPct": -11.11,
      "detail": "recommendations=0.32, market=0.36"
    },
    {
      "symbol": "TANM",
      "issue": "recommendation price differs from market",
      "recommendationPrice": 5.25,
      "sourcePrice": 5.89,
      "diffPct": -10.87,
      "detail": "recommendations=5.25, market=5.89"
    },
    {
      "symbol": "MCQE",
      "issue": "recommendation price differs from market",
      "recommendationPrice": 172.1,
      "sourcePrice": 192.22,
      "diffPct": -10.47,
      "detail": "recommendations=172.1, market=192.22"
    },
    {
      "symbol": "WKOL",
      "issue": "recommendation price differs from market",
      "recommendationPrice": 281.12,
      "sourcePrice": 313.68,
      "diffPct": -10.38,
      "detail": "recommendations=281.12, market=313.68"
    },
    {
      "symbol": "WCDF",
      "issue": "recommendation price differs from market",
      "recommendationPrice": 506.06,
      "sourcePrice": 564.53,
      "diffPct": -10.36,
      "detail": "recommendations=506.06, market=564.53"
    },
    {
      "symbol": "GSSC",
      "issue": "recommendation price differs from market",
      "recommendationPrice": 244.44,
      "sourcePrice": 272,
      "diffPct": -10.13,
      "detail": "recommendations=244.44, market=272"
    },
    {
      "symbol": "COSG",
      "issue": "recommendation price differs from market",
      "recommendationPrice": 1.52,
      "sourcePrice": 1.69,
      "diffPct": -10.06,
      "detail": "recommendations=1.52, market=1.69"
    },
    {
      "symbol": "RUBX",
      "issue": "recommendation price differs from market",
      "recommendationPrice": 12.35,
      "sourcePrice": 13.71,
      "diffPct": -9.92,
      "detail": "recommendations=12.35, market=13.71"
    },
    {
      "symbol": "ALUM",
      "issue": "recommendation price differs from market",
      "recommendationPrice": 21.45,
      "sourcePrice": 23.8,
      "diffPct": -9.87,
      "detail": "recommendations=21.45, market=23.8"
    },
    {
      "symbol": "ETEL",
      "issue": "recommendation price differs from market",
      "recommendationPrice": 93.98,
      "sourcePrice": 104.15,
      "diffPct": -9.76,
      "detail": "recommendations=93.98, market=104.15"
    },
    {
      "symbol": "GMCI",
      "issue": "recommendation price differs from market",
      "recommendationPrice": 1.86,
      "sourcePrice": 2.06,
      "diffPct": -9.71,
      "detail": "recommendations=1.86, market=2.06"
    },
    {
      "symbol": "EFIH",
      "issue": "recommendation price differs from market",
      "recommendationPrice": 20.93,
      "sourcePrice": 23.16,
      "diffPct": -9.63,
      "detail": "recommendations=20.93, market=23.16"
    },
    {
      "symbol": "CIRA",
      "issue": "recommendation price differs from market",
      "recommendationPrice": 28.8,
      "sourcePrice": 31.81,
      "diffPct": -9.46,
      "detail": "recommendations=28.8, market=31.81"
    },
    {
      "symbol": "AIDC",
      "issue": "recommendation price differs from market",
      "recommendationPrice": 0.67,
      "sourcePrice": 0.74,
      "diffPct": -9.46,
      "detail": "recommendations=0.67, market=0.74"
    },
    {
      "symbol": "DAPH",
      "issue": "recommendation price differs from market",
      "recommendationPrice": 82.29,
      "sourcePrice": 90.85,
      "diffPct": -9.42,
      "detail": "recommendations=82.29, market=90.85"
    },
    {
      "symbol": "EEII",
      "issue": "recommendation price differs from market",
      "recommendationPrice": 2.5,
      "sourcePrice": 2.76,
      "diffPct": -9.42,
      "detail": "recommendations=2.5, market=2.76"
    },
    {
      "symbol": "IDRE",
      "issue": "recommendation price differs from market",
      "recommendationPrice": 43.65,
      "sourcePrice": 48.08,
      "diffPct": -9.21,
      "detail": "recommendations=43.65, market=48.08"
    },
    {
      "symbol": "CERA",
      "issue": "recommendation price differs from market",
      "recommendationPrice": 1.22,
      "sourcePrice": 1.34,
      "diffPct": -8.96,
      "detail": "recommendations=1.22, market=1.34"
    },
    {
      "symbol": "MPCI",
      "issue": "recommendation price differs from market",
      "recommendationPrice": 246,
      "sourcePrice": 269.84,
      "diffPct": -8.83,
      "detail": "recommendations=246, market=269.84"
    },
    {
      "symbol": "COMI",
      "issue": "recommendation price differs from market",
      "recommendationPrice": 127.4,
      "sourcePrice": 139.65,
      "diffPct": -8.77,
      "detail": "recommendations=127.4, market=139.65"
    },
    {
      "symbol": "ACGC",
      "issue": "recommendation price differs from market",
      "recommendationPrice": 9.23,
      "sourcePrice": 10.1,
      "diffPct": -8.61,
      "detail": "recommendations=9.23, market=10.1"
    },
    {
      "symbol": "AFDI",
      "issue": "recommendation price differs from market",
      "recommendationPrice": 44.34,
      "sourcePrice": 48.49,
      "diffPct": -8.56,
      "detail": "recommendations=44.34, market=48.49"
    },
    {
      "symbol": "RTVC",
      "issue": "recommendation price differs from market",
      "recommendationPrice": 3.79,
      "sourcePrice": 4.14,
      "diffPct": -8.45,
      "detail": "recommendations=3.79, market=4.14"
    },
    {
      "symbol": "RREI",
      "issue": "recommendation price differs from market",
      "recommendationPrice": 3.47,
      "sourcePrice": 3.78,
      "diffPct": -8.2,
      "detail": "recommendations=3.47, market=3.78"
    },
    {
      "symbol": "ACAMD",
      "issue": "recommendation price differs from market",
      "recommendationPrice": 2.25,
      "sourcePrice": 2.45,
      "diffPct": -8.16,
      "detail": "recommendations=2.25, market=2.45"
    },
    {
      "symbol": "APSW",
      "issue": "recommendation price differs from market",
      "recommendationPrice": 8.48,
      "sourcePrice": 9.23,
      "diffPct": -8.13,
      "detail": "recommendations=8.48, market=9.23"
    },
    {
      "symbol": "QNBE",
      "issue": "recommendation price differs from market",
      "recommendationPrice": 52.58,
      "sourcePrice": 57.18,
      "diffPct": -8.04,
      "detail": "recommendations=52.58, market=57.18"
    },
    {
      "symbol": "EXPA",
      "issue": "recommendation price differs from market",
      "recommendationPrice": 18.33,
      "sourcePrice": 19.93,
      "diffPct": -8.03,
      "detail": "recommendations=18.33, market=19.93"
    },
    {
      "symbol": "PRCL",
      "issue": "recommendation price differs from market",
      "recommendationPrice": 33,
      "sourcePrice": 35.87,
      "diffPct": -8,
      "detail": "recommendations=33, market=35.87"
    },
    {
      "symbol": "NCCW",
      "issue": "recommendation price differs from market",
      "recommendationPrice": 6.16,
      "sourcePrice": 6.69,
      "diffPct": -7.92,
      "detail": "recommendations=6.16, market=6.69"
    },
    {
      "symbol": "CCAP",
      "issue": "recommendation price differs from market",
      "recommendationPrice": 5.04,
      "sourcePrice": 5.45,
      "diffPct": -7.52,
      "detail": "recommendations=5.04, market=5.45"
    },
    {
      "symbol": "OCDI",
      "issue": "recommendation price differs from market",
      "recommendationPrice": 25.36,
      "sourcePrice": 27.4,
      "diffPct": -7.45,
      "detail": "recommendations=25.36, market=27.4"
    },
    {
      "symbol": "EASB",
      "issue": "recommendation price differs from market",
      "recommendationPrice": 7.54,
      "sourcePrice": 8.14,
      "diffPct": -7.37,
      "detail": "recommendations=7.54, market=8.14"
    },
    {
      "symbol": "EALR",
      "issue": "recommendation price differs from market",
      "recommendationPrice": 339.92,
      "sourcePrice": 365.95,
      "diffPct": -7.11,
      "detail": "recommendations=339.92, market=365.95"
    },
    {
      "symbol": "FERC",
      "issue": "recommendation price differs from market",
      "recommendationPrice": 73.55,
      "sourcePrice": 79.12,
      "diffPct": -7.04,
      "detail": "recommendations=73.55, market=79.12"
    },
    {
      "symbol": "AREH",
      "issue": "recommendation price differs from market",
      "recommendationPrice": 1.56,
      "sourcePrice": 1.46,
      "diffPct": 6.85,
      "detail": "recommendations=1.56, market=1.46"
    },
    {
      "symbol": "MOSC",
      "issue": "recommendation price differs from market",
      "recommendationPrice": 267.72,
      "sourcePrice": 287.32,
      "diffPct": -6.82,
      "detail": "recommendations=267.72, market=287.32"
    },
    {
      "symbol": "NAPR",
      "issue": "recommendation price differs from market",
      "recommendationPrice": 26.32,
      "sourcePrice": 28.23,
      "diffPct": -6.77,
      "detail": "recommendations=26.32, market=28.23"
    },
    {
      "symbol": "ABUK",
      "issue": "recommendation price differs from market",
      "recommendationPrice": 67.94,
      "sourcePrice": 72.64,
      "diffPct": -6.47,
      "detail": "recommendations=67.94, market=72.64"
    },
    {
      "symbol": "MFSC",
      "issue": "recommendation price differs from market",
      "recommendationPrice": 49.48,
      "sourcePrice": 46.48,
      "diffPct": 6.45,
      "detail": "recommendations=49.48, market=46.48"
    },
    {
      "symbol": "AJWA",
      "issue": "recommendation price differs from market",
      "recommendationPrice": 179.07,
      "sourcePrice": 168.29,
      "diffPct": 6.41,
      "detail": "recommendations=179.07, market=168.29"
    },
    {
      "symbol": "TMGH",
      "issue": "recommendation price differs from market",
      "recommendationPrice": 94.97,
      "sourcePrice": 101.41,
      "diffPct": -6.35,
      "detail": "recommendations=94.97, market=101.41"
    },
    {
      "symbol": "ELEC",
      "issue": "recommendation price differs from market",
      "recommendationPrice": 2.1,
      "sourcePrice": 2.24,
      "diffPct": -6.25,
      "detail": "recommendations=2.1, market=2.24"
    },
    {
      "symbol": "EGBE",
      "issue": "recommendation price differs from market",
      "recommendationPrice": 0.45,
      "sourcePrice": 0.48,
      "diffPct": -6.25,
      "detail": "recommendations=0.45, market=0.48"
    },
    {
      "symbol": "SNFC",
      "issue": "recommendation price differs from market",
      "recommendationPrice": 12.08,
      "sourcePrice": 11.38,
      "diffPct": 6.15,
      "detail": "recommendations=12.08, market=11.38"
    },
    {
      "symbol": "EGCH",
      "issue": "recommendation price differs from market",
      "recommendationPrice": 12.25,
      "sourcePrice": 13.04,
      "diffPct": -6.06,
      "detail": "recommendations=12.25, market=13.04"
    },
    {
      "symbol": "OIH",
      "issue": "recommendation price differs from market",
      "recommendationPrice": 1.41,
      "sourcePrice": 1.5,
      "diffPct": -6,
      "detail": "recommendations=1.41, market=1.5"
    },
    {
      "symbol": "VLMRA",
      "issue": "recommendation price differs from market",
      "recommendationPrice": 28.2,
      "sourcePrice": 29.99,
      "diffPct": -5.97,
      "detail": "recommendations=28.2, market=29.99"
    },
    {
      "symbol": "PRMH",
      "issue": "recommendation price differs from market",
      "recommendationPrice": 2.57,
      "sourcePrice": 2.73,
      "diffPct": -5.86,
      "detail": "recommendations=2.57, market=2.73"
    },
    {
      "symbol": "ZEOT",
      "issue": "recommendation price differs from market",
      "recommendationPrice": 11.04,
      "sourcePrice": 11.71,
      "diffPct": -5.72,
      "detail": "recommendations=11.04, market=11.71"
    },
    {
      "symbol": "MOED",
      "issue": "recommendation price differs from market",
      "recommendationPrice": 0.68,
      "sourcePrice": 0.72,
      "diffPct": -5.56,
      "detail": "recommendations=0.68, market=0.72"
    },
    {
      "symbol": "AMOC",
      "issue": "recommendation price differs from market",
      "recommendationPrice": 7.76,
      "sourcePrice": 8.21,
      "diffPct": -5.48,
      "detail": "recommendations=7.76, market=8.21"
    },
    {
      "symbol": "ADIB",
      "issue": "recommendation price differs from market",
      "recommendationPrice": 46.64,
      "sourcePrice": 49.3,
      "diffPct": -5.4,
      "detail": "recommendations=46.64, market=49.3"
    },
    {
      "symbol": "SWDY",
      "issue": "recommendation price differs from market",
      "recommendationPrice": 87,
      "sourcePrice": 91.9,
      "diffPct": -5.33,
      "detail": "recommendations=87, market=91.9"
    },
    {
      "symbol": "ADCI",
      "issue": "recommendation price differs from market",
      "recommendationPrice": 240.97,
      "sourcePrice": 254.53,
      "diffPct": -5.33,
      "detail": "recommendations=240.97, market=254.53"
    },
    {
      "symbol": "COPR",
      "issue": "recommendation price differs from market",
      "recommendationPrice": 0.36,
      "sourcePrice": 0.38,
      "diffPct": -5.26,
      "detail": "recommendations=0.36, market=0.38"
    },
    {
      "symbol": "SPIN",
      "issue": "recommendation price differs from market",
      "recommendationPrice": 14.17,
      "sourcePrice": 14.95,
      "diffPct": -5.22,
      "detail": "recommendations=14.17, market=14.95"
    },
    {
      "symbol": "EGAS",
      "issue": "recommendation price differs from market",
      "recommendationPrice": 49.63,
      "sourcePrice": 52.35,
      "diffPct": -5.2,
      "detail": "recommendations=49.63, market=52.35"
    },
    {
      "symbol": "FWRY",
      "issue": "recommendation price differs from market",
      "recommendationPrice": 18.37,
      "sourcePrice": 19.35,
      "diffPct": -5.06,
      "detail": "recommendations=18.37, market=19.35"
    },
    {
      "symbol": "EGAL",
      "issue": "recommendation price differs from market",
      "recommendationPrice": 285.88,
      "sourcePrice": 301.04,
      "diffPct": -5.04,
      "detail": "recommendations=285.88, market=301.04"
    },
    {
      "symbol": "SDTI",
      "issue": "recommendation price differs from market",
      "recommendationPrice": 46.44,
      "sourcePrice": 48.86,
      "diffPct": -4.95,
      "detail": "recommendations=46.44, market=48.86"
    },
    {
      "symbol": "MFPC",
      "issue": "recommendation price differs from market",
      "recommendationPrice": 35.72,
      "sourcePrice": 37.55,
      "diffPct": -4.87,
      "detail": "recommendations=35.72, market=37.55"
    },
    {
      "symbol": "MICH",
      "issue": "recommendation price differs from market",
      "recommendationPrice": 37.54,
      "sourcePrice": 39.44,
      "diffPct": -4.82,
      "detail": "recommendations=37.54, market=39.44"
    },
    {
      "symbol": "ALCN",
      "issue": "recommendation price differs from market",
      "recommendationPrice": 28.34,
      "sourcePrice": 29.7,
      "diffPct": -4.58,
      "detail": "recommendations=28.34, market=29.7"
    },
    {
      "symbol": "SPMD",
      "issue": "recommendation price differs from market",
      "recommendationPrice": 0.43,
      "sourcePrice": 0.45,
      "diffPct": -4.44,
      "detail": "recommendations=0.43, market=0.45"
    },
    {
      "symbol": "ACAP",
      "issue": "recommendation price differs from market",
      "recommendationPrice": 8.56,
      "sourcePrice": 8.95,
      "diffPct": -4.36,
      "detail": "recommendations=8.56, market=8.95"
    },
    {
      "symbol": "AIHC",
      "issue": "recommendation price differs from market",
      "recommendationPrice": 0.47,
      "sourcePrice": 0.49,
      "diffPct": -4.08,
      "detail": "recommendations=0.47, market=0.49"
    },
    {
      "symbol": "SAUD",
      "issue": "recommendation price differs from market",
      "recommendationPrice": 21.09,
      "sourcePrice": 21.95,
      "diffPct": -3.92,
      "detail": "recommendations=21.09, market=21.95"
    },
    {
      "symbol": "PHDC",
      "issue": "recommendation price differs from market",
      "recommendationPrice": 14.58,
      "sourcePrice": 15.17,
      "diffPct": -3.89,
      "detail": "recommendations=14.58, market=15.17"
    },
    {
      "symbol": "BTFH",
      "issue": "recommendation price differs from market",
      "recommendationPrice": 2.97,
      "sourcePrice": 3.09,
      "diffPct": -3.88,
      "detail": "recommendations=2.97, market=3.09"
    },
    {
      "symbol": "NEDA",
      "issue": "recommendation price differs from market",
      "recommendationPrice": 2.75,
      "sourcePrice": 2.86,
      "diffPct": -3.85,
      "detail": "recommendations=2.75, market=2.86"
    },
    {
      "symbol": "JUFO",
      "issue": "recommendation price differs from market",
      "recommendationPrice": 29.99,
      "sourcePrice": 28.9,
      "diffPct": 3.77,
      "detail": "recommendations=29.99, market=28.9"
    },
    {
      "symbol": "VALU",
      "issue": "recommendation price differs from market",
      "recommendationPrice": 12.05,
      "sourcePrice": 12.5,
      "diffPct": -3.6,
      "detail": "recommendations=12.05, market=12.5"
    },
    {
      "symbol": "CANA",
      "issue": "recommendation price differs from market",
      "recommendationPrice": 35.74,
      "sourcePrice": 37,
      "diffPct": -3.41,
      "detail": "recommendations=35.74, market=37"
    },
    {
      "symbol": "KORA",
      "issue": "recommendation price differs from market",
      "recommendationPrice": 3.45,
      "sourcePrice": 3.34,
      "diffPct": 3.29,
      "detail": "recommendations=3.45, market=3.34"
    },
    {
      "symbol": "BINV",
      "issue": "recommendation price differs from market",
      "recommendationPrice": 46.04,
      "sourcePrice": 47.57,
      "diffPct": -3.22,
      "detail": "recommendations=46.04, market=47.57"
    },
    {
      "symbol": "ASCM",
      "issue": "recommendation price differs from market",
      "recommendationPrice": 59.26,
      "sourcePrice": 61.08,
      "diffPct": -2.98,
      "detail": "recommendations=59.26, market=61.08"
    },
    {
      "symbol": "ARCC",
      "issue": "recommendation price differs from market",
      "recommendationPrice": 55.44,
      "sourcePrice": 57.11,
      "diffPct": -2.92,
      "detail": "recommendations=55.44, market=57.11"
    },
    {
      "symbol": "ECAP",
      "issue": "recommendation price differs from market",
      "recommendationPrice": 32.72,
      "sourcePrice": 33.7,
      "diffPct": -2.91,
      "detail": "recommendations=32.72, market=33.7"
    },
    {
      "symbol": "IRON",
      "issue": "recommendation price differs from market",
      "recommendationPrice": 32.21,
      "sourcePrice": 31.31,
      "diffPct": 2.87,
      "detail": "recommendations=32.21, market=31.31"
    },
    {
      "symbol": "PHAR",
      "issue": "recommendation price differs from market",
      "recommendationPrice": 88.21,
      "sourcePrice": 90.75,
      "diffPct": -2.8,
      "detail": "recommendations=88.21, market=90.75"
    },
    {
      "symbol": "CSAG",
      "issue": "recommendation price differs from market",
      "recommendationPrice": 32.58,
      "sourcePrice": 33.51,
      "diffPct": -2.78,
      "detail": "recommendations=32.58, market=33.51"
    },
    {
      "symbol": "MENA",
      "issue": "recommendation price differs from market",
      "recommendationPrice": 6.89,
      "sourcePrice": 7.08,
      "diffPct": -2.68,
      "detail": "recommendations=6.89, market=7.08"
    },
    {
      "symbol": "SVCE",
      "issue": "recommendation price differs from market",
      "recommendationPrice": 9.63,
      "sourcePrice": 9.38,
      "diffPct": 2.67,
      "detail": "recommendations=9.63, market=9.38"
    },
    {
      "symbol": "ORHD",
      "issue": "recommendation price differs from market",
      "recommendationPrice": 38.25,
      "sourcePrice": 39.3,
      "diffPct": -2.67,
      "detail": "recommendations=38.25, market=39.3"
    },
    {
      "symbol": "ORWE",
      "issue": "recommendation price differs from market",
      "recommendationPrice": 22.39,
      "sourcePrice": 23,
      "diffPct": -2.65,
      "detail": "recommendations=22.39, market=23"
    },
    {
      "symbol": "SCTS",
      "issue": "recommendation price differs from market",
      "recommendationPrice": 626.62,
      "sourcePrice": 611.44,
      "diffPct": 2.48,
      "detail": "recommendations=626.62, market=611.44"
    },
    {
      "symbol": "ETRS",
      "issue": "recommendation price differs from market",
      "recommendationPrice": 10.6,
      "sourcePrice": 10.85,
      "diffPct": -2.3,
      "detail": "recommendations=10.6, market=10.85"
    },
    {
      "symbol": "EFID",
      "issue": "recommendation price differs from market",
      "recommendationPrice": 27.37,
      "sourcePrice": 27.99,
      "diffPct": -2.22,
      "detail": "recommendations=27.37, market=27.99"
    },
    {
      "symbol": "CIEB",
      "issue": "recommendation price differs from market",
      "recommendationPrice": 23.92,
      "sourcePrice": 24.45,
      "diffPct": -2.17,
      "detail": "recommendations=23.92, market=24.45"
    },
    {
      "symbol": "POUL",
      "issue": "recommendation price differs from market",
      "recommendationPrice": 38,
      "sourcePrice": 38.82,
      "diffPct": -2.11,
      "detail": "recommendations=38, market=38.82"
    },
    {
      "symbol": "DOMT",
      "issue": "recommendation price differs from market",
      "recommendationPrice": 27.23,
      "sourcePrice": 26.68,
      "diffPct": 2.06,
      "detail": "recommendations=27.23, market=26.68"
    },
    {
      "symbol": "EMFD",
      "issue": "recommendation price differs from market",
      "recommendationPrice": 11.56,
      "sourcePrice": 11.8,
      "diffPct": -2.03,
      "detail": "recommendations=11.56, market=11.8"
    },
    {
      "symbol": "OLFI",
      "issue": "recommendation price differs from market",
      "recommendationPrice": 22.29,
      "sourcePrice": 22.75,
      "diffPct": -2.02,
      "detail": "recommendations=22.29, market=22.75"
    },
    {
      "symbol": "DGTZ",
      "issue": "recommendation price differs from market",
      "recommendationPrice": 2.51,
      "sourcePrice": 2.56,
      "diffPct": -1.95,
      "detail": "recommendations=2.51, market=2.56"
    },
    {
      "symbol": "ROTO",
      "issue": "recommendation price differs from market",
      "recommendationPrice": 41.48,
      "sourcePrice": 42.29,
      "diffPct": -1.92,
      "detail": "recommendations=41.48, market=42.29"
    },
    {
      "symbol": "ATQA",
      "issue": "recommendation price differs from market",
      "recommendationPrice": 9.47,
      "sourcePrice": 9.65,
      "diffPct": -1.87,
      "detail": "recommendations=9.47, market=9.65"
    },
    {
      "symbol": "CNFN",
      "issue": "recommendation price differs from market",
      "recommendationPrice": 4.76,
      "sourcePrice": 4.85,
      "diffPct": -1.86,
      "detail": "recommendations=4.76, market=4.85"
    },
    {
      "symbol": "UBEE",
      "issue": "recommendation price differs from market",
      "recommendationPrice": 13.47,
      "sourcePrice": 13.72,
      "diffPct": -1.82,
      "detail": "recommendations=13.47, market=13.72"
    },
    {
      "symbol": "FAIT",
      "issue": "recommendation price differs from market",
      "recommendationPrice": 36.98,
      "sourcePrice": 37.65,
      "diffPct": -1.78,
      "detail": "recommendations=36.98, market=37.65"
    },
    {
      "symbol": "AXPH",
      "issue": "recommendation price differs from market",
      "recommendationPrice": 1212.35,
      "sourcePrice": 1233.15,
      "diffPct": -1.69,
      "detail": "recommendations=1212.35, market=1233.15"
    },
    {
      "symbol": "VLMR",
      "issue": "recommendation price differs from market",
      "recommendationPrice": 0.67,
      "sourcePrice": 0.66,
      "diffPct": 1.52,
      "detail": "recommendations=0.67, market=0.66"
    },
    {
      "symbol": "ICID",
      "issue": "recommendation price differs from market",
      "recommendationPrice": 7.98,
      "sourcePrice": 8.1,
      "diffPct": -1.48,
      "detail": "recommendations=7.98, market=8.1"
    },
    {
      "symbol": "CLHO",
      "issue": "recommendation price differs from market",
      "recommendationPrice": 16.5,
      "sourcePrice": 16.74,
      "diffPct": -1.43,
      "detail": "recommendations=16.5, market=16.74"
    },
    {
      "symbol": "MBSC",
      "issue": "recommendation price differs from market",
      "recommendationPrice": 242.18,
      "sourcePrice": 245.67,
      "diffPct": -1.42,
      "detail": "recommendations=242.18, market=245.67"
    },
    {
      "symbol": "BONY",
      "issue": "recommendation price differs from market",
      "recommendationPrice": 4.88,
      "sourcePrice": 4.95,
      "diffPct": -1.41,
      "detail": "recommendations=4.88, market=4.95"
    },
    {
      "symbol": "RACC",
      "issue": "recommendation price differs from market",
      "recommendationPrice": 9.85,
      "sourcePrice": 9.98,
      "diffPct": -1.3,
      "detail": "recommendations=9.85, market=9.98"
    },
    {
      "symbol": "KZPC",
      "issue": "recommendation price differs from market",
      "recommendationPrice": 8.47,
      "sourcePrice": 8.58,
      "diffPct": -1.28,
      "detail": "recommendations=8.47, market=8.58"
    },
    {
      "symbol": "ORAS",
      "issue": "recommendation price differs from market",
      "recommendationPrice": 720.42,
      "sourcePrice": 711.55,
      "diffPct": 1.25,
      "detail": "recommendations=720.42, market=711.55"
    },
    {
      "symbol": "ISMQ",
      "issue": "recommendation price differs from market",
      "recommendationPrice": 9.34,
      "sourcePrice": 9.23,
      "diffPct": 1.19,
      "detail": "recommendations=9.34, market=9.23"
    },
    {
      "symbol": "CICH",
      "issue": "recommendation price differs from market",
      "recommendationPrice": 11.87,
      "sourcePrice": 12.01,
      "diffPct": -1.17,
      "detail": "recommendations=11.87, market=12.01"
    },
    {
      "symbol": "MPCO",
      "issue": "recommendation price differs from market",
      "recommendationPrice": 1.84,
      "sourcePrice": 1.86,
      "diffPct": -1.08,
      "detail": "recommendations=1.84, market=1.86"
    },
    {
      "symbol": "MTIE",
      "issue": "recommendation price differs from market",
      "recommendationPrice": 9.34,
      "sourcePrice": 9.44,
      "diffPct": -1.06,
      "detail": "recommendations=9.34, market=9.44"
    },
    {
      "symbol": "ELWA",
      "issue": "recommendation price differs from market",
      "recommendationPrice": 1.95,
      "sourcePrice": 1.93,
      "diffPct": 1.04,
      "detail": "recommendations=1.95, market=1.93"
    },
    {
      "symbol": "OBRI",
      "issue": "recommendation price differs from market",
      "recommendationPrice": 34.94,
      "sourcePrice": 35.3,
      "diffPct": -1.02,
      "detail": "recommendations=34.94, market=35.3"
    },
    {
      "symbol": "FAITA",
      "issue": "recommendation price differs from market",
      "recommendationPrice": 0.99,
      "sourcePrice": 0.98,
      "diffPct": 1.02,
      "detail": "recommendations=0.99, market=0.98"
    },
    {
      "symbol": "RAYA",
      "issue": "recommendation price differs from market",
      "recommendationPrice": 7.67,
      "sourcePrice": 7.6,
      "diffPct": 0.92,
      "detail": "recommendations=7.67, market=7.6"
    },
    {
      "symbol": "GPIM",
      "issue": "recommendation price differs from market",
      "recommendationPrice": 1.11,
      "sourcePrice": 1.12,
      "diffPct": -0.89,
      "detail": "recommendations=1.11, market=1.12"
    },
    {
      "symbol": "TALM",
      "issue": "recommendation price differs from market",
      "recommendationPrice": 15.8,
      "sourcePrice": 15.93,
      "diffPct": -0.82,
      "detail": "recommendations=15.8, market=15.93"
    }
  ],
  "note": "If all internal sources show the same stale price, the report cannot know the true live price. Run workflow or improve the fetch source."
}