{
  "ok": true,
  "generatedAt": "2026-07-07T15:39:17.763Z",
  "mode": "public_delayed_session_monitor",
  "disclaimer_ar": "تقرير جلسة للمراقبة فقط وليس توصية تنفيذ.",
  "summary_ar": "تم تحليل 221 سهم من الكاش الحالي. مراقبة شراء: 36. حذر/تخفيف: 48. جودة بيانات منخفضة: 0.",
  "numbers": {
    "cachedRows": 221,
    "watchBuy": 36,
    "riskReduce": 48,
    "lowQuality": 0,
    "alerts": 21,
    "universeCoveragePct": 93.3,
    "missingFromCache": 12
  },
  "topWatch": [
    {
      "symbol": "SVCE",
      "price": 9.63,
      "opportunityScore": 95,
      "decision": "مراقبة شراء مشروطة",
      "reason": "فوق Pivot + السعر إيجابي + سيولة قوية"
    },
    {
      "symbol": "NIPH",
      "price": 180.06,
      "opportunityScore": 94,
      "decision": "مراقبة شراء مشروطة",
      "reason": "فوق Pivot + السعر إيجابي + سيولة قوية"
    },
    {
      "symbol": "OCDI",
      "price": 25.36,
      "opportunityScore": 92,
      "decision": "مراقبة شراء مشروطة",
      "reason": "فوق Pivot + السعر إيجابي + سيولة قوية + قريب من دعم"
    },
    {
      "symbol": "RUBX",
      "price": 12.35,
      "opportunityScore": 91,
      "decision": "مراقبة شراء مشروطة",
      "reason": "فوق Pivot + السعر إيجابي + سيولة قوية"
    },
    {
      "symbol": "PRCL",
      "price": 33,
      "opportunityScore": 91,
      "decision": "مراقبة شراء مشروطة",
      "reason": "فوق Pivot + السعر إيجابي + سيولة مقبولة"
    },
    {
      "symbol": "ISMQ",
      "price": 9.34,
      "opportunityScore": 88,
      "decision": "مراقبة شراء مشروطة",
      "reason": "فوق Pivot + السعر إيجابي + سيولة قوية"
    },
    {
      "symbol": "DTPP",
      "price": 199.26,
      "opportunityScore": 87,
      "decision": "مراقبة شراء مشروطة",
      "reason": "فوق Pivot + السعر إيجابي + سيولة مقبولة"
    },
    {
      "symbol": "HRHO",
      "price": 26.96,
      "opportunityScore": 86,
      "decision": "مراقبة شراء مشروطة",
      "reason": "فوق Pivot + السعر إيجابي + سيولة مقبولة + قريب من دعم"
    },
    {
      "symbol": "MTIE",
      "price": 9.34,
      "opportunityScore": 86,
      "decision": "مراقبة شراء مشروطة",
      "reason": "فوق Pivot + السعر إيجابي + سيولة مقبولة"
    },
    {
      "symbol": "PRDC",
      "price": 7.7,
      "opportunityScore": 85,
      "decision": "مراقبة شراء مشروطة",
      "reason": "فوق Pivot + السعر إيجابي + سيولة مقبولة"
    },
    {
      "symbol": "MPCI",
      "price": 246,
      "opportunityScore": 85,
      "decision": "مراقبة شراء مشروطة",
      "reason": "فوق Pivot + السعر إيجابي + سيولة مقبولة"
    },
    {
      "symbol": "BONY",
      "price": 4.88,
      "opportunityScore": 84,
      "decision": "مراقبة شراء مشروطة",
      "reason": "فوق Pivot + السعر إيجابي + سيولة مقبولة + قريب من دعم"
    },
    {
      "symbol": "OBRI",
      "price": 34.94,
      "opportunityScore": 84,
      "decision": "مراقبة شراء مشروطة",
      "reason": "فوق Pivot + السعر إيجابي + سيولة مقبولة"
    },
    {
      "symbol": "AXPH",
      "price": 1212.35,
      "opportunityScore": 84,
      "decision": "مراقبة شراء مشروطة",
      "reason": "فوق Pivot + السعر إيجابي + سيولة ضعيفة"
    },
    {
      "symbol": "MFPC",
      "price": 35.72,
      "opportunityScore": 83,
      "decision": "مراقبة شراء مشروطة",
      "reason": "فوق Pivot + السعر إيجابي + سيولة مقبولة + قريب من دعم"
    }
  ],
  "riskWatch": [
    {
      "symbol": "ALCN",
      "price": 28.34,
      "riskScore": 12,
      "reason": "تحت Pivot + سيولة ضعيفة + قريب من دعم"
    },
    {
      "symbol": "ADIB",
      "price": 46.64,
      "riskScore": 50,
      "reason": "تحت Pivot + ضغط سعري سلبي + سيولة مقبولة + قريب من دعم + مساحة قبل المقاومة"
    },
    {
      "symbol": "IRON",
      "price": 32.21,
      "riskScore": 30,
      "reason": "تحت Pivot + ضغط سعري سلبي + سيولة ضعيفة + قريب من دعم + مساحة قبل المقاومة"
    },
    {
      "symbol": "VALU",
      "price": 12.05,
      "riskScore": 30,
      "reason": "تحت Pivot + ضغط سعري سلبي + سيولة ضعيفة + قريب من دعم + مساحة قبل المقاومة"
    },
    {
      "symbol": "CLHO",
      "price": 16.5,
      "riskScore": 50,
      "reason": "تحت Pivot + ضغط سعري سلبي + سيولة مقبولة + قريب من دعم"
    },
    {
      "symbol": "TAQA",
      "price": 14.46,
      "riskScore": 65,
      "reason": "تحت Pivot + ضغط سعري سلبي + سيولة مقبولة + كسر دعم"
    },
    {
      "symbol": "ORWE",
      "price": 22.39,
      "riskScore": 26,
      "reason": "تحت Pivot + سيولة ضعيفة + قريب من دعم + قريب جدًا من المقاومة"
    },
    {
      "symbol": "CICH",
      "price": 11.87,
      "riskScore": 26,
      "reason": "تحت Pivot + سيولة ضعيفة + قريب من دعم + قريب جدًا من المقاومة"
    },
    {
      "symbol": "EGBE",
      "price": 0.45,
      "riskScore": 12,
      "reason": "تحت Pivot + السعر إيجابي + سيولة ضعيفة + قريب من دعم"
    },
    {
      "symbol": "MOIL",
      "price": 0.48,
      "riskScore": 26,
      "reason": "تحت Pivot + السعر إيجابي + سيولة ضعيفة + قريب جدًا من المقاومة"
    },
    {
      "symbol": "BINV",
      "price": 46.04,
      "riskScore": 12,
      "reason": "تحت Pivot + سيولة ضعيفة + قريب من دعم"
    },
    {
      "symbol": "CSAG",
      "price": 32.58,
      "riskScore": 12,
      "reason": "تحت Pivot + السعر إيجابي + سيولة ضعيفة + قريب من دعم"
    },
    {
      "symbol": "MIPH",
      "price": 658.44,
      "riskScore": 12,
      "reason": "تحت Pivot + السعر إيجابي + سيولة ضعيفة + قريب من دعم"
    },
    {
      "symbol": "AMES",
      "price": 60.51,
      "riskScore": 50,
      "reason": "تحت Pivot + ضغط سعري سلبي + سيولة مقبولة + قريب من دعم + مساحة قبل المقاومة"
    },
    {
      "symbol": "MOIN",
      "price": 23.73,
      "riskScore": 30,
      "reason": "تحت Pivot + ضغط سعري سلبي + سيولة ضعيفة + قريب من دعم + مساحة قبل المقاومة"
    }
  ]
}